[
  {
    "partNumber": 1,
    "partName": "B P GUPTA GIRLS INTER COLLEGE, GOVIND NAGAR ROOM NO.1"
  },
  {
    "partNumber": 2,
    "partName": "B P GUPTA GIRLS INTER COLLEGE, GOVIND NAGAR ROOM NO.2"
  },
  {
    "partNumber": 3,
    "partName": "SARASWATI VIDYA MANDIR INTER COLLEGE GOVIND NAGAR ROOM NO. 1"
  },
  {
    "partNumber": 4,
    "partName": "SARASWATI VIDYA MANDIR INTER COLLEGE GOVIND NAGAR ROOM NO. 2"
  },
  {
    "partNumber": 5,
    "partName": "SARASWATI VIDYA MANDIR INTER COLLEGE GOVIND NAGAR ROOM NO. 3"
  },
  {
    "partNumber": 6,
    "partName": "SARASWATI VIDYA MANDIR INTER COLLEGE GOVIND NAGAR ROOM NO. 4"
  },
  {
    "partNumber": 7,
    "partName": "SARASWATI VIDYA MANDIR INTER COLLEGE GOVIND NAGAR ROOM NO. 5"
  },
  {
    "partNumber": 8,
    "partName": "SARASWATI VIDYA MANDIR INTER COLLEGE GOVIND NAGAR ROOM NO. 6"
  },
  {
    "partNumber": 9,
    "partName": "SARASWATI VIDYA MANDIR INTER COLLEGE GOVIND NAGAR ROOM NO. 7"
  },
  {
    "partNumber": 10,
    "partName": "ARYA KANYA INTER COLLEGE ROOM NO 1 CHAK 124 C  GOVIND NAGAR"
  },
  {
    "partNumber": 11,
    "partName": "D.B.S. COLLEGE ROOM NO 1 CHAK 124B GOVIND NAGAR"
  },
  {
    "partNumber": 12,
    "partName": "D.B.S. COLLEGE  ROOM NO 2 CHAK 124 B  GOVIND NAGAR"
  },
  {
    "partNumber": 13,
    "partName": "D.B.S. COLLEGE ROOM NO 3 CHAK 124 B GOVIND NAGAR"
  },
  {
    "partNumber": 14,
    "partName": "D.B.S. COLLEGE  ROOM NO 4 CHAK 124 B GOVIND NAGAR"
  },
  {
    "partNumber": 15,
    "partName": "D.B.S. COLLEGE ROOM NO 5 CHAK 124 B GOVIND NAGAR"
  },
  {
    "partNumber": 16,
    "partName": "ARYA KANYA INTER COLLEGE ROOM NO 2 CHAK 124 C GOVIND NAGAR"
  },
  {
    "partNumber": 17,
    "partName": "ARYA KANYA INTER COLLEGE ROOM NO 3 CHAK 124 C GOVIND NAGAR"
  },
  {
    "partNumber": 18,
    "partName": "ARYA KANYA INTER COLLEGE ROOM NO 4 CHAK 124 C  GOVIND NAGAR"
  },
  {
    "partNumber": 19,
    "partName": "ARYA KANYA INTER COLLEGE ROOM NO 5 CHAK 124 C  GOVIND NAGAR"
  },
  {
    "partNumber": 20,
    "partName": "N.M.P. GANDHI SMARAK INTER COLLEGE ROOM NO 1 CHAK 125 GOVIND NAGAR"
  },
  {
    "partNumber": 21,
    "partName": "N.M.P. GANDHI SMARAK INTER COLLEGEROOM NO 2 125  GOVIND NAGAR"
  },
  {
    "partNumber": 22,
    "partName": "N.M.P. GANDHI SMARAK INTER COLLEGE ROOM N0 3 125 GOVIND NAGAR"
  },
  {
    "partNumber": 23,
    "partName": "N.M.P. GANDHI SMARAK INTER COLLEGE ROOM NO 4 125 GOVIND NAGAR"
  },
  {
    "partNumber": 24,
    "partName": "N.M.P. GANDHI SMARAK INTER COLLEGE  ROOM NO 5 125 GOVIND NAGAR"
  },
  {
    "partNumber": 25,
    "partName": "N.M.P. GANDHI SMARAK INTER COLLEGE  ROOM NO 6 125 GOVIND NAGAR"
  },
  {
    "partNumber": 26,
    "partName": "N.M.P. GANDHI SMARAK INTER COLLEGE  ROOM NO 7 125 GOVIND NAGAR"
  },
  {
    "partNumber": 27,
    "partName": "STEPPING STONE INTER COLLEGE  GOVIND NAGAR, ROOM NO. 1"
  },
  {
    "partNumber": 28,
    "partName": "STEPPING STONE INTER COLLEGE  GOVIND NAGAR, ROOM NO. 2"
  },
  {
    "partNumber": 29,
    "partName": "COMPOSITE VIDYALAYA KANYA PARAMPURWA GOVIND NAGAR ROOM NO. 1"
  },
  {
    "partNumber": 30,
    "partName": "COMPOSITE VIDYALAYA KANYA PARAMPURWA GOVIND NAGAR ROOM NO. 2"
  },
  {
    "partNumber": 31,
    "partName": "COMPOSITE VIDYALAYA KANYA PARAMPURWA GOVIND NAGAR ROOM NO. 3"
  },
  {
    "partNumber": 32,
    "partName": "SWEET HOME HIGHER SECONDARY SCHOOL GOVIND NAGAR ROOM NO. 1"
  },
  {
    "partNumber": 33,
    "partName": "SWEET HOME HIGHER SECONDARY SCHOOL GOVIND NAGAR ROOM NO. 2"
  },
  {
    "partNumber": 34,
    "partName": "VIMAL MEMORIAL PUBLIC SCHOOL JUHI LAL COLONY ROOM NO 1"
  },
  {
    "partNumber": 35,
    "partName": "VIMAL MEMORIAL PUBLIC SCHOOL JUHI LAL COLONY ROOM NO 2"
  },
  {
    "partNumber": 36,
    "partName": "VIMAL MEMORIAL PUBLIC SCHOOL JUHI LAL COLONY ROOM NO 3"
  },
  {
    "partNumber": 37,
    "partName": "PR. VIDHYALAYA  KANYA  JUHI KALA JUHI DEPO KE PASS KIDWAI NAGAR ROOM NO. 1"
  },
  {
    "partNumber": 38,
    "partName": "PR. VIDHYALAYA  KANYA  JUHI KALA JUHI DEPO KE PASS KIDWAI NAGAR ROOM NO. 2"
  },
  {
    "partNumber": 39,
    "partName": "PANDIT SURYA NARAYAN UCHCHTAR MADHYAMIK VIDHYALAYA JUHI BARA DEVI ROOM NO.1"
  },
  {
    "partNumber": 40,
    "partName": "PANDIT SURYA NARAYAN UCHCHTAR MADHYAMIK VIDHYALAYA JUHI BARA DEVI ROOM NO.2"
  },
  {
    "partNumber": 41,
    "partName": "PANDIT SURYA NARAYAN UCHCHTAR MADHYAMIK VIDHYALAYA JUHI BARA DEVI ROOM NO.3"
  },
  {
    "partNumber": 42,
    "partName": "PANDIT SURYA NARAYAN UCHCHTAR MADHYAMIK VIDHYALAYA JUHI BARA DEVI ROOM NO.4"
  },
  {
    "partNumber": 43,
    "partName": "COMPOSITE VIDAYLAYA NIRALA NAGAR BHAWAN SANKHYA-1 ROOM NO. 1"
  },
  {
    "partNumber": 44,
    "partName": "COMPOSITE VIDAYLAYA NIRALA NAGAR BHAWAN SANKHYA-1 ROOM NO. 2"
  },
  {
    "partNumber": 45,
    "partName": "COMPOSITE VIDAYLAYA NIRALA NAGAR BHAWAN SANKHYA-1 ROOM NO. 3"
  },
  {
    "partNumber": 46,
    "partName": "RAJYA KARAMCHARI BEEMA HOSPITAL, BINOVA NAGAR, ROOM NO. 1"
  },
  {
    "partNumber": 47,
    "partName": "RAJYA KARAMCHARI BEEMA HOSPITAL, BINOVA NAGAR, ROOM NO. 2"
  },
  {
    "partNumber": 48,
    "partName": "RAJYA KARAMCHARI BEEMA HOSPITAL, BINOVA NAGAR, ROOM NO. 3"
  },
  {
    "partNumber": 49,
    "partName": "RAJYA KARAMCHARI BEEMA HOSPITAL, BINOVA NAGAR, ROOM NO. 4"
  },
  {
    "partNumber": 50,
    "partName": "RAJYA KARAMCHARI BEEMA HOSPITAL, BINOVA NAGAR, ROOM NO. 5"
  },
  {
    "partNumber": 51,
    "partName": "PR VIDHYALAYA KANYA  JUHI KALA JUHI DEPO KE PASS KIDWAI NAGAR ROOM NO. 3"
  },
  {
    "partNumber": 52,
    "partName": "COMPOSITE VIDAYLAYA NIRALA NAGAR BHAWAN SANKHYA-2 ROOM NO 1"
  },
  {
    "partNumber": 53,
    "partName": "COMPOSITE VIDAYLAYA NIRALA NAGAR BHAWAN SANKHYA-2 ROOM NO 2"
  },
  {
    "partNumber": 54,
    "partName": "COMPOSITE VIDAYLAYA NIRALA NAGAR BHAWAN SANKHYA-2 ROOM NO 3"
  },
  {
    "partNumber": 55,
    "partName": "COMPOSITE VIDAYLAYA NIRALA NAGAR BHAWAN SANKHYA-2 ROOM NO 4"
  },
  {
    "partNumber": 56,
    "partName": "COMPOSITE VIDAYLAYA NIRALA NAGAR BHAWAN SANKHYA-2 ROOM NO 5"
  },
  {
    "partNumber": 57,
    "partName": "COMPOSITE VIDAYLAYA NIRALA NAGAR BHAWAN SANKHYA-2 ROOM NO 6"
  },
  {
    "partNumber": 58,
    "partName": "COMPOSITE VIDAYLAYA NIRALA NAGAR BHAWAN SANKHYA-1 ROOM NO. 4"
  },
  {
    "partNumber": 59,
    "partName": "SUBHASH SMARAK INTER COLLEGE ROOM NO 1 .127  SAKET NAGAR"
  },
  {
    "partNumber": 60,
    "partName": "SUBHASH  SMARAK INTER COLLEGE ROOM N0 2. 127 SAKET NAGAR"
  },
  {
    "partNumber": 61,
    "partName": "SUBHASH SMARAK INTER COLLEGE  ROOM NO 3 . 127  SAKET NAGAR"
  },
  {
    "partNumber": 62,
    "partName": "SUBHASH SMARAK INTER COLLEGE ROOM NO 4. 127  SAKET NAGAR"
  },
  {
    "partNumber": 63,
    "partName": "SUBHASH SMARAK INTER COLLEGE ROOM NO 5. 127 SAKET NAGAR"
  },
  {
    "partNumber": 64,
    "partName": "SUBHASH SMARAK INTER COLLEGE ROOM NO 6 .127  SAKET NAGAR"
  },
  {
    "partNumber": 65,
    "partName": "SUBHASH SMARAK INTER COLLEGE ROOM NO 7 .127 SAKET NAGAR"
  },
  {
    "partNumber": 66,
    "partName": "SUBHASH SMARAK INTER COLLEGE  ROOM NO 8. 127 SAKET NAGAR"
  },
  {
    "partNumber": 67,
    "partName": "SUBHASH SMARAK INTER COLLEGE  ROOM NO 9 . 127 SAKET NAGAR"
  },
  {
    "partNumber": 68,
    "partName": "SOUTH CITY PUBLIC SCHOOL BASANT VIHAR  ROOM NO 1"
  },
  {
    "partNumber": 69,
    "partName": "SOUTH CITY PUBLIC SCHOOL BASANT VIHAR  ROOM NO 2"
  },
  {
    "partNumber": 70,
    "partName": "SOUTH CITY PUBLIC SCHOOL BASANT VIHAR  ROOM NO 3"
  },
  {
    "partNumber": 71,
    "partName": "SOUTH CITY PUBLIC SCHOOL BASANT VIHAR  ROOM NO 4"
  },
  {
    "partNumber": 72,
    "partName": "DR. SONELAL PATEL SENIOR  SECONDARY SCHOOL   ROOM N0 1 JUHI HAMIRPUR ROAD"
  },
  {
    "partNumber": 73,
    "partName": "DR. SONELAL PATEL SENIOR  SECONDARY SCHOOL  ROOM NO 2 JUHI HAMIRPUR ROAD"
  },
  {
    "partNumber": 74,
    "partName": "DR  SONELAL PATEL SENIOR  SECONDARY SCHOOL  ROOM NO 3 JUHI HAMIRPUR ROAD"
  },
  {
    "partNumber": 75,
    "partName": "DR. SONELAL PATEL SENIOR  SECONDARY SCHOOL ROOM NO 4 JUHI HAMIRPUR ROAD"
  },
  {
    "partNumber": 76,
    "partName": "\"PR. VIDHYALAYA JUHI LABOR COLONEY SECOND KIDWAI NAGAR ROOM NO. 1 \""
  },
  {
    "partNumber": 77,
    "partName": "SUBHASH SMARAK PUBLIC SCHOOL SAKET NAGAR ROOM NO 1"
  },
  {
    "partNumber": 78,
    "partName": "SUBHASH SMARAK PUBLIC SCHOOL SAKET NAGAR ROOM NO 2"
  },
  {
    "partNumber": 79,
    "partName": "\"PR. VIDHYALAYA JUHI LABOR COLONEY SECOND KIDWAI NAGAR ROOM NO. 2 \""
  },
  {
    "partNumber": 80,
    "partName": "VIRENDRA SWAROOP INSITITUTE OF COMPUTER SAKET NAGAR ROOM NO 1"
  },
  {
    "partNumber": 81,
    "partName": "VIRENDRA SWAROOP INSITITUTE OF COMPUTER SAKET NAGAR ROOM NO 2"
  },
  {
    "partNumber": 82,
    "partName": "VIRENDRA SWAROOP INSITITUTE OF COMPUTER SAKET NAGAR ROOM NO 3"
  },
  {
    "partNumber": 83,
    "partName": "KAUSHALYA DEVI U.M.BALIKA VIDHYALAYA   KIDWAI NAGAR ROOM NO 1"
  },
  {
    "partNumber": 84,
    "partName": "KAUSHALYA DEVI U.M.BALIKA VIDHYALAYA   KIDWAI NAGAR ROOM NO 2"
  },
  {
    "partNumber": 85,
    "partName": "KAUSHALYA DEVI U.M.BALIKA VIDHYALAYA   KIDWAI NAGAR ROOM NO 3"
  },
  {
    "partNumber": 86,
    "partName": "KAUSHALYA DEVI U.M.BALIKA VIDHYALAYA   KIDWAI NAGAR ROOM NO 4"
  },
  {
    "partNumber": 87,
    "partName": "KAUSHALYA DEVI U.M.BALIKA VIDHYALAYA   KIDWAI NAGAR ROOM NO 5"
  },
  {
    "partNumber": 88,
    "partName": "KAUSHALYA DEVI U.M.BALIKA VIDHYALAYA   KIDWAI NAGAR ROOM NO 6"
  },
  {
    "partNumber": 89,
    "partName": "KAUSHALYA DEVI U.M.BALIKA VIDHYALAYA   KIDWAI NAGAR ROOM NO 7"
  },
  {
    "partNumber": 90,
    "partName": "KAUSHALYA DEVI U.M.BALIKA VIDHYALAYA   KIDWAI NAGAR ROOM NO 8"
  },
  {
    "partNumber": 91,
    "partName": "ANNAPURNA MEMORIAL JR. HIGH SCHOOL, CHHANGAMAL KA HATA JUHI ROOM NO 1"
  },
  {
    "partNumber": 92,
    "partName": "VIRENDRA SWAROOP INSITITUTE OF COMPUTER SAKET NAGAR ROOM NO 4"
  },
  {
    "partNumber": 93,
    "partName": "LAUGHING BUDDHA ACADEMY JUHI BINOVA NAGAR ROOM NO 1"
  },
  {
    "partNumber": 94,
    "partName": "LAUGHING BUDDHA ACADEMY JUHI BINOVA NAGAR ROOM NO 2"
  },
  {
    "partNumber": 95,
    "partName": "LAUGHING BUDDHA ACADEMY JUHI BINOVA NAGAR ROOM NO 3"
  },
  {
    "partNumber": 96,
    "partName": "M G SHISHU VIDYA MANDIR 127/41 JUHI BAMBURIHA  ROOM NO.1"
  },
  {
    "partNumber": 97,
    "partName": "M G SHISHU VIDYA MANDIR 127/41 JUHI BAMBURIHA  ROOM NO.2"
  },
  {
    "partNumber": 98,
    "partName": "M G SHISHU VIDYA MANDIR 127/41 JUHI BAMBURIHA  ROOM NO.3"
  },
  {
    "partNumber": 99,
    "partName": "BABURAM DIXIT BALIKA VIDHYALAYA  KESHAV  NAGAR ROOM NO 1"
  },
  {
    "partNumber": 100,
    "partName": "BABURAM DIXIT BALIKA VIDHYALAYA  KESHAV  NAGAR ROOM NO 2"
  },
  {
    "partNumber": 101,
    "partName": "BABURAM DIXIT BALIKA VIDHYALAYA  KESHAV  NAGAR ROOM NO 3"
  },
  {
    "partNumber": 102,
    "partName": "BABURAM DIXIT BALIKA VIDHYALAYA  KESHAV  NAGAR ROOM  NO 4"
  },
  {
    "partNumber": 103,
    "partName": "BABURAM DIXIT BALIKA VIDHYALAYA  KESHAV  NAGAR ROOM NO 5"
  },
  {
    "partNumber": 104,
    "partName": "BABURAM DIXIT BALIKA VIDHYALAYA  KESHAV  NAGAR ROOM NO 6"
  },
  {
    "partNumber": 105,
    "partName": "BABURAM DIXIT BALIKA VIDHYALAYA  KESHAV  NAGAR ROOM NO 7"
  },
  {
    "partNumber": 106,
    "partName": "SHIVAJI INTER COLLEGE W BLOCK KESHAV  NAGAR ROOM NO1"
  },
  {
    "partNumber": 107,
    "partName": "SHIVAJI INTER COLLEGE W BLOCK KESHAV  NAGAR ROOM NO2"
  },
  {
    "partNumber": 108,
    "partName": "SHIVAJI INTER COLLEGE W BLOCK KESHAV  NAGAR ROOM NO 3"
  },
  {
    "partNumber": 109,
    "partName": "SHIVAJI INTER COLLEGE W BLOCK KESHAV  NAGAR ROOM NO 4"
  },
  {
    "partNumber": 110,
    "partName": "SHIVAJI INTER COLLEGE W BLOCK KESHAV  NAGAR ROOM NO 5"
  },
  {
    "partNumber": 111,
    "partName": "SHIVAJI INTER COLLEGE W BLOCK KESHAV  NAGAR ROOM NO 6"
  },
  {
    "partNumber": 112,
    "partName": "MOHAN VIDHYA MANDIR INTER COLLEGE (BOYS) GOVIND NAGAR ROOM NO 1"
  },
  {
    "partNumber": 113,
    "partName": "MOHAN VIDHYA MANDIR INTER COLLEGE (BOYS) GOVIND NAGAR ROOM NO 2"
  },
  {
    "partNumber": 114,
    "partName": "MOHAN VIDHYA MANDIR INTER COLLEGE (BOYS) GOVIND NAGAR ROOM NO 3"
  },
  {
    "partNumber": 115,
    "partName": "MOHAN VIDHYA MANDIR INTER COLLEGE (BOYS) GOVIND NAGAR ROOM NO 4"
  },
  {
    "partNumber": 116,
    "partName": "MOHAN VIDHYA MANDIR INTER COLLEGE (BOYS) GOVIND NAGAR ROOM NO 5"
  },
  {
    "partNumber": 117,
    "partName": "MOHAN VIDHYA MANDIR INTER COLLEGE (BOYS) GOVIND NAGAR ROOM NO 6"
  },
  {
    "partNumber": 118,
    "partName": "MOHAN VIDHYA MANDIR INTER COLLEGE (BOYS) GOVIND NAGAR ROOM NO 7"
  },
  {
    "partNumber": 119,
    "partName": "MOHAN VIDHYA MANDIR INTER COLLEGE (BOYS) GOVIND NAGAR ROOM NO 8"
  },
  {
    "partNumber": 120,
    "partName": "MOHAN VIDHYA MANDIR INTER COLLEGE (BOYS) GOVIND NAGAR ROOM NO 9"
  },
  {
    "partNumber": 121,
    "partName": "ARYA BHUTT INTER COLLAGE DAMODAR NAGAR KANPUR ROOM NO.1"
  },
  {
    "partNumber": 122,
    "partName": "ARYA BHUTT INTER COLLAGE DAMODAR NAGAR KANPUR ROOM NO.2"
  },
  {
    "partNumber": 123,
    "partName": "ARYA BHUTT INTER COLLAGE DAMODAR NAGAR KANPUR ROOM NO.3"
  },
  {
    "partNumber": 124,
    "partName": "ARYA BHUTT INTER COLLAGE DAMODAR NAGAR KANPUR ROOM NO.4"
  },
  {
    "partNumber": 125,
    "partName": "ARYA BHUTT INTER COLLAGE DAMODAR NAGAR KANPUR ROOM NO.5"
  },
  {
    "partNumber": 126,
    "partName": "ARYA BHUTT INTER COLLAGE DAMODAR NAGAR KANPUR ROOM NO.6"
  },
  {
    "partNumber": 127,
    "partName": "ARYA BHUTT INTER COLLAGE DAMODAR NAGAR KANPUR ROOM NO.7"
  },
  {
    "partNumber": 128,
    "partName": "COMPOSITE VIDAYLAYA BARRA NAI BASTI ROOM NO 1"
  },
  {
    "partNumber": 129,
    "partName": "COMPOSITE VIDAYLAYA BARRA NAI BASTI ROOM NO 2"
  },
  {
    "partNumber": 130,
    "partName": "COMPOSITE VIDAYLAYA BARRA NAI BASTI ROOM NO 3"
  },
  {
    "partNumber": 131,
    "partName": "COMPOSITE VIDAYLAYA NAI BASTI BARRA ROOM NO 1"
  },
  {
    "partNumber": 132,
    "partName": "COMPOSITE VIDAYLAYA BARRA NAI BASTI ROOM NO 4"
  },
  {
    "partNumber": 133,
    "partName": "COMPOSITE VIDAYLAYA NAI BASTI BARRA ROOM NO 2"
  },
  {
    "partNumber": 134,
    "partName": "RAMRATI SMARAK VIDHYA MANDIR, B BLOCK BARRA 8 ROOM NO 1"
  },
  {
    "partNumber": 135,
    "partName": "RAMRATI SMARAK VIDHYA MANDIR, B BLOCK BARRA 8 ROOM NO 2"
  },
  {
    "partNumber": 136,
    "partName": "RAMRATI SMARAK VIDHYA MANDIR, B BLOCK BARRA 8 ROOM NO 3"
  },
  {
    "partNumber": 137,
    "partName": "RAMRATI SMARAK VIDHYA MANDIR, B BLOCK BARRA 8 ROOM NO 4"
  },
  {
    "partNumber": 138,
    "partName": "RAMRATI SMARAK VIDHYA MANDIR, B BLOCK BARRA 8 ROOM NO 5"
  },
  {
    "partNumber": 139,
    "partName": "RAMRATI SMARAK VIDHYA MANDIR, B BLOCK BARRA 8 ROOM NO 6"
  },
  {
    "partNumber": 140,
    "partName": "P.V.N. PUBLIC INTER COLLEGE, SECTOR-D, BARRA-8 ROOM NO 1"
  },
  {
    "partNumber": 141,
    "partName": "P.V.N. PUBLIC INTER COLLEGE, SECTOR-D, BARRA-8 ROOM NO 2"
  },
  {
    "partNumber": 142,
    "partName": "P.V.N. PUBLIC INTER COLLEGE, SECTOR-D, BARRA-8 ROOM NO 3"
  },
  {
    "partNumber": 143,
    "partName": "P.V.N. PUBLIC INTER COLLEGE, SECTOR-D, BARRA-8 ROOM NO 4"
  },
  {
    "partNumber": 144,
    "partName": "VIVEKANAND PUBLIC INTER COLLAGE BARRA 8 ROOM NO.1"
  },
  {
    "partNumber": 145,
    "partName": "VIVEKANAND PUBLIC INTER COLLAGE BARRA 8 ROOM NO.2"
  },
  {
    "partNumber": 146,
    "partName": "VIVEKANAND PUBLIC INTER COLLAGE BARRA 8 ROOM NO.3"
  },
  {
    "partNumber": 147,
    "partName": "VIVEKANAND PUBLIC INTER COLLAGE BARRA 8 ROOM NO.4"
  },
  {
    "partNumber": 148,
    "partName": "VIVEKANAND PUBLIC INTER COLLAGE BARRA 8 ROOM NO.5"
  },
  {
    "partNumber": 149,
    "partName": "MERRY JESUS EDUCATION CENTRE BARRA-8  ROOM NO 1"
  },
  {
    "partNumber": 150,
    "partName": "MERRY JESUS EDUCATION CENTRE BARRA-8  ROOM NO 2"
  },
  {
    "partNumber": 151,
    "partName": "MERRY JESUS EDUCATION CENTRE BARRA-8  ROOM NO 3"
  },
  {
    "partNumber": 152,
    "partName": "MERRY JESUS EDUCATION CENTRE BARRA-8  ROOM NO 4"
  },
  {
    "partNumber": 153,
    "partName": "MERRY JESUS EDUCATION CENTRE BARRA-8  ROOM NO 5"
  },
  {
    "partNumber": 154,
    "partName": "MERRY JESUS EDUCATION CENTRE BARRA-8  ROOM NO 6"
  },
  {
    "partNumber": 155,
    "partName": "MERRY JESUS EDUCATION CENTRE BARRA-8  ROOM NO 7"
  },
  {
    "partNumber": 156,
    "partName": "PR. PATHSHALA GOVIND NAGAR DWITIY VISHWA BANK BARRA  H BLOCK NEAR PANI KI TANKI ANDHA KUAN (EAST) ROOM NO 1"
  },
  {
    "partNumber": 157,
    "partName": "PR. PATHSHALA GOVIND NAGAR DWITIY VISHWA BANK BARRA  H BLOCK NEAR PANI KI TANKI ANDHA KUAN (EAST) ROOM NO 2"
  },
  {
    "partNumber": 158,
    "partName": "PR. PATHSHALA GOVIND NAGAR DWITIY VISHWA BANK BARRA  H BLOCK NEAR PANI KI TANKI ANDHA KUAN (EAST) ROOM NO 3"
  },
  {
    "partNumber": 159,
    "partName": "VIKASIKA NEHRU MEMORIAL INTER COLLEGE, VISHWABANK BARRA ROOM NO 1"
  },
  {
    "partNumber": 160,
    "partName": "VIKASIKA NEHRU MEMORIAL INTER COLLEGE, VISHWABANK BARRA ROOM NO 2"
  },
  {
    "partNumber": 161,
    "partName": "VIKASIKA NEHRU MEMORIAL INTER COLLEGE, VISHWABANK BARRA ROOM NO 3"
  },
  {
    "partNumber": 162,
    "partName": "VIKASIKA NEHRU MEMORIAL INTER COLLEGE, VISHWABANK BARRA ROOM NO 4"
  },
  {
    "partNumber": 163,
    "partName": "PRATHMIK VIDYALAYA RAIPURWA SECTOR B VISHWA BANK BARRA KANPUR ROOM NO 1"
  },
  {
    "partNumber": 164,
    "partName": "PRATHMIK VIDYALAYA RAIPURWA SECTOR B VISHWA BANK BARRA KANPUR  ROOM NO 2"
  },
  {
    "partNumber": 165,
    "partName": "S.D.CONVENT SECTOR B-1314 VISHWABANK ROOM NO 1"
  },
  {
    "partNumber": 166,
    "partName": "S.D.CONVENT SECTOR B-1314 VISHWABANK ROOM NO 2"
  },
  {
    "partNumber": 167,
    "partName": "PRATHMIK VIDYALAYA HULAGANJ A VISHWA BANK BARRA ROOM NO 1"
  },
  {
    "partNumber": 168,
    "partName": "PRATHMIK VIDYALAYA HULAGANJ A VISHWA BANK BARRA ROOM NO 2"
  },
  {
    "partNumber": 169,
    "partName": "PRATHMIK VIDYALAYA HULAGANJ A VISHWA BANK BARRA ROOM NO 3"
  },
  {
    "partNumber": 170,
    "partName": "PRATHMIK VIDYALAYA HULAGANJ A VISHWA BANK BARRA ROOM NO 4"
  },
  {
    "partNumber": 171,
    "partName": "PRATHMIK VIDALAYA MALVIYA NAGAR SECTOR-D VISHWA BANK BARRA ROOM NO 1"
  },
  {
    "partNumber": 172,
    "partName": "PRATHMIK VIDALAYA MALVIYA NAGAR SECTOR-D VISHWA BANK BARRA ROOM NO 2"
  },
  {
    "partNumber": 173,
    "partName": "PRATHMIK VIDALAYA MALVIYA NAGAR SECTOR-D VISHWA BANK BARRA ROOM NO 3"
  },
  {
    "partNumber": 174,
    "partName": "PRATHMIK VIDALAYA MALVIYA NAGAR SECTOR-D VISHWA BANK BARRA ROOM NO 4"
  },
  {
    "partNumber": 175,
    "partName": "SUBEDAR SMAARAK BAL VIDHYALAYA VISHWABANK  BARRA SECTOR H ROOM NO 1"
  },
  {
    "partNumber": 176,
    "partName": "SUBEDAR SMAARAK BAL VIDHYALAYA VISHWABANK  BARRA SECTOR H ROOM NO 2"
  },
  {
    "partNumber": 177,
    "partName": "SUBEDAR SMAARAK BAL VIDHYALAYA VISHWABANK  BARRA SECTOR H ROOM NO 3"
  },
  {
    "partNumber": 178,
    "partName": "SUBEDAR SMAARAK BAL VIDHYALAYA VISHWABANK  BARRA SECTOR H ROOM NO 4"
  },
  {
    "partNumber": 179,
    "partName": "NURTURE INTERNATIONAL SCHOOL BARRA 2 ROOM NO 1"
  },
  {
    "partNumber": 180,
    "partName": "NURTURE INTERNATIONAL SCHOOL BARRA 2 ROOM NO 2"
  },
  {
    "partNumber": 181,
    "partName": "MANYATA PRAPT SUDHA DEVI MISHRA VIDHYALAYA  CHHEDI SINGH KA PURWA MANOHAR NAGAR BARRA-2 ROOM NO 1"
  },
  {
    "partNumber": 182,
    "partName": "MANYATA PRAPT SUDHA DEVI MISHRA VIDHYALAYA  CHHEDI SINGH KA PURWA MANOHAR NAGAR BARRA-2 ROOM NO 2"
  },
  {
    "partNumber": 183,
    "partName": "R.S. EDUCATION CENTRE BALIKA H.S. SCHOOL BARRA-2  ROOM NO 3"
  },
  {
    "partNumber": 184,
    "partName": "R.S. EDUCATION CENTRE INTER COLLEGE PLOT  NO. 7 KUNTI NAGAR BARRA-2 ROOM NO 1"
  },
  {
    "partNumber": 185,
    "partName": "R.S. EDUCATION CENTRE INTER COLLEGE PLOT  NO. 7 KUNTI NAGAR BARRA-2 ROOM NO 2"
  },
  {
    "partNumber": 186,
    "partName": "R.S. EDUCATION CENTRE INTER COLLEGE PLOT  NO. 7 KUNTI NAGAR BARRA-2 ROOM NO 3"
  },
  {
    "partNumber": 187,
    "partName": "R.S. EDUCATION CENTRE INTER COLLEGE PLOT  NO. 7 KUNTI NAGAR BARRA-2 ROOM NO 4"
  },
  {
    "partNumber": 188,
    "partName": "R.S. EDUCATION CENTRE BALIKA H.S. SCHOOL BARRA-2  ROOM NO 1"
  },
  {
    "partNumber": 189,
    "partName": "R.S. EDUCATION CENTRE BALIKA H.S. SCHOOL BARRA-2  ROOM NO 2"
  },
  {
    "partNumber": 190,
    "partName": "SARDAR PATEL  SCHOOL BARRA-2 M.I. SECTOR ROOM NO 1"
  },
  {
    "partNumber": 191,
    "partName": "SARDAR PATEL  SCHOOL BARRA-2 M.I. SECTOR ROOM NO 2"
  },
  {
    "partNumber": 192,
    "partName": "SARDAR PATEL  SCHOOL BARRA-2 M.I. SECTOR ROOM NO 3"
  },
  {
    "partNumber": 193,
    "partName": "SARDAR PATEL  SCHOOL BARRA-2 M.I. SECTOR ROOM NO 4"
  },
  {
    "partNumber": 194,
    "partName": "SARDAR PATEL  SCHOOL BARRA-2 M.I. SECTOR ROOM NO 5"
  },
  {
    "partNumber": 195,
    "partName": "SARDAR PATEL  SCHOOL BARRA-2 M.I. SECTOR ROOM NO 6"
  },
  {
    "partNumber": 196,
    "partName": "SARDAR PATEL  SCHOOL BARRA-2 M.I. SECTOR ROOM NO 7"
  },
  {
    "partNumber": 197,
    "partName": "VIVEKANAND BALIKA INTER COLLEGE BARRA-2 ROOM NO 1"
  },
  {
    "partNumber": 198,
    "partName": "VIVEKANAND BALIKA INTER COLLEGE BARRA-2 ROOM NO 2"
  },
  {
    "partNumber": 199,
    "partName": "VIVEKANAND BALIKA INTER COLLEGE BARRA-2ROOM NO 3"
  },
  {
    "partNumber": 200,
    "partName": "VIVEKANAND BALIKA INTER COLLEGE BARRA-2 ROOM NO 4"
  },
  {
    "partNumber": 201,
    "partName": "R.S. JUNIOR PUBLIC SCHOOL CHHEDISINGH KA PURWA BARRA 2 ROOM NO 1"
  },
  {
    "partNumber": 202,
    "partName": "R.S. JUNIOR PUBLIC SCHOOL CHHEDISINGH KA PURWA BARRA 2 ROOM NO 2"
  },
  {
    "partNumber": 203,
    "partName": "POORNACHANDRA VIDHYA NIKETAN BARRA-2, ROOM NO. 1"
  },
  {
    "partNumber": 204,
    "partName": "R.S. JUNIOR PUBLIC SCHOOL CHHEDISINGH KA PURWA BARRA 2 ROOM NO 3"
  },
  {
    "partNumber": 205,
    "partName": "R.S. JUNIOR PUBLIC SCHOOL CHHEDISINGH KA PURWA BARRA 2 ROOM NO 4"
  },
  {
    "partNumber": 206,
    "partName": "POORNACHANDRA VIDHYA NIKETAN BARRA-2, ROOM NO. 2"
  },
  {
    "partNumber": 207,
    "partName": "POORNACHANDRA VIDHYA NIKETAN BARRA-2, ROOM NO. 3"
  },
  {
    "partNumber": 208,
    "partName": "POORNACHANDRA VIDHYA NIKETAN BARRA-2, ROOM NO. 4"
  },
  {
    "partNumber": 209,
    "partName": "BHARTIYA VIDYA PEETH GIRLS JUNIOR HIGH SCHOOL 160 Y BLOCK KIDWAI NAGAR ROOM NO.1"
  },
  {
    "partNumber": 210,
    "partName": "BHARTIYA VIDYA PEETH GIRLS JUNIOR HIGH SCHOOL 160 Y BLOCK KIDWAI NAGAR ROOM NO.2"
  },
  {
    "partNumber": 211,
    "partName": "PREM BALIKA INTER COLLEGE HAMIRPUR  ROAD ROOM NO 1"
  },
  {
    "partNumber": 212,
    "partName": "PREM BALIKA INTER COLLEGE HAMIRPUR  ROAD ROOM NO 2"
  },
  {
    "partNumber": 213,
    "partName": "PREM BALIKA INTER COLLEGE HAMIRPUR  ROAD ROOM NO 3"
  },
  {
    "partNumber": 214,
    "partName": "ARYAWART SARASWATI SHISHU MANDIR HAMEERPUR ROAD ROOM NO 1"
  },
  {
    "partNumber": 215,
    "partName": "ARYAWART SARASWATI SHISHU MANDIR HAMEERPUR ROAD ROOM NO 2"
  },
  {
    "partNumber": 216,
    "partName": "ARYAWART SARASWATI SHISHU MANDIR HAMEERPUR ROAD ROOM NO 3"
  },
  {
    "partNumber": 217,
    "partName": "ARYAVRAT INTER COLLEGE PASHUPATI NAGAR ROOM NO 1"
  },
  {
    "partNumber": 218,
    "partName": "ARYAVRAT INTER COLLEGE PASHUPATI NAGAR ROOM NO 2"
  },
  {
    "partNumber": 219,
    "partName": "ARYAVRAT INTER COLLEGE PASHUPATI NAGAR ROOM NO 3"
  },
  {
    "partNumber": 220,
    "partName": "PREM BALIKA INTER COLLEGE HAMIRPUR  ROAD ROOM NO 4"
  },
  {
    "partNumber": 221,
    "partName": "PREM BALIKA INTER COLLEGE HAMIRPUR  ROAD ROOM NO 5"
  },
  {
    "partNumber": 222,
    "partName": "PREM BALIKA INTER COLLEGE HAMIRPUR  ROAD ROOM NO 6"
  },
  {
    "partNumber": 223,
    "partName": "PREM BALIKA INTER COLLEGE HAMIRPUR  ROAD ROOM NO 7"
  },
  {
    "partNumber": 224,
    "partName": "ARYAWART SARASWATI SHISHU MANDIR HAMEERPUR ROAD ROOM NO 4"
  },
  {
    "partNumber": 225,
    "partName": "SHANTI NIKETAN VIDHYALAYA  ANAND VIHAR NEAR KATH KA PUL ROOM NO 1 NAUBASTA"
  },
  {
    "partNumber": 226,
    "partName": "SHANTI NIKETAN VIDHYALAYA  ANAND VIHAR NEAR KATH KA PULROOM NO 2 NAUBASTA"
  },
  {
    "partNumber": 227,
    "partName": "SHANTI NIKETAN VIDHYALAYA  ANAND VIHAR NEAR KATH KA PULROOM NO 3 NAUBASTA"
  },
  {
    "partNumber": 228,
    "partName": "SHANTI NIKETAN VIDHYALAYA  ANAND VIHAR NEAR KATH KA PULROOM NO 4 NAUBASTA"
  },
  {
    "partNumber": 229,
    "partName": "SHANTI NIKETAN VIDHYALAYA  ANAND VIHAR NEAR KATH KA PULROOM NO 5 NAUBASTA"
  },
  {
    "partNumber": 230,
    "partName": "J.N.P.N BALIKA INTER COLLEGE  ANAND VIHAR ROOM NO 1 NAUBASTA"
  },
  {
    "partNumber": 231,
    "partName": "J.N.P.N BALIKA INTER COLLEGE  ANAND VIHAR ROOM NO 2 NAUBASTA"
  },
  {
    "partNumber": 232,
    "partName": "J.N.P.N BALIKA INTER COLLEGE  ANAND VIHAR ROOM NO 3 NAUBASTA"
  },
  {
    "partNumber": 233,
    "partName": "J.N.P.N BALIKA INTER COLLEGE  ANAND VIHAR ROOM NO 4 NAUBASTA"
  },
  {
    "partNumber": 234,
    "partName": "J.N.P.N BALIKA INTER COLLEGE  ANAND VIHAR ROOM NO 5 NAUBASTA"
  },
  {
    "partNumber": 235,
    "partName": "J.N.P.N. INTER COLLEGE, ANAND VIHAR, NAUBASTA ROOM NO 1"
  },
  {
    "partNumber": 236,
    "partName": "J.N.P.N. INTER COLLEGE, ANAND VIHAR, NAUBASTA ROOM NO 2"
  },
  {
    "partNumber": 237,
    "partName": "J.N.P.N. INTER COLLEGE, ANAND VIHAR, NAUBASTA ROOM NO 3"
  },
  {
    "partNumber": 238,
    "partName": "DAYANAD SARASWATI INTER COLLEGE 1451 HANUMANT VIHAR NAUBASTA ROOM NO 1"
  },
  {
    "partNumber": 239,
    "partName": "DAYANAD SARASWATI INTER COLLEGE 1451 HANUMANT VIHAR NAUBASTA ROOM NO 2"
  },
  {
    "partNumber": 240,
    "partName": "DAYANAD SARASWATI INTER COLLEGE 1451 HANUMANT VIHAR NAUBASTA ROOM NO 3"
  },
  {
    "partNumber": 241,
    "partName": "DAYANAD SARASWATI INTER COLLEGE 1451 HANUMANT VIHAR NAUBASTA ROOM NO 4"
  },
  {
    "partNumber": 242,
    "partName": "ARJUN VIDHLAYA J.  H.HANUMANT VIHAR  NAUBASTA KANPUR ROOM NO 1"
  },
  {
    "partNumber": 243,
    "partName": "ARJUN VIDHLAYA J.  H.HANUMANT VIHAR  NAUBASTA KANPUR ROOM NO 2"
  },
  {
    "partNumber": 244,
    "partName": "ARJUN VIDHLAYA J.  H.HANUMANT VIHAR  NAUBASTA KANPUR ROOM NO 3"
  },
  {
    "partNumber": 245,
    "partName": "J.N.P.N. BALIKA INTER COLLEGE ANAND VIHAR NAUBASTA  ROOM NO 6"
  },
  {
    "partNumber": 246,
    "partName": "J.N.P.N. BALIKA INTER COLLEGE ANAND VIHAR NAUBASTA  ROOM NO 7"
  },
  {
    "partNumber": 247,
    "partName": "J S MISSION CONVENT SCHOOL DAMODAR NAGAR KANPUR ROOM NO. 1"
  },
  {
    "partNumber": 248,
    "partName": "J S MISSION CONVENT SCHOOL DAMODAR NAGAR KANPUR ROOM NO. 2"
  },
  {
    "partNumber": 249,
    "partName": "J S MISSION CONVENT SCHOOL DAMODAR NAGAR KANPUR ROOM NO. 3"
  },
  {
    "partNumber": 250,
    "partName": "J S MISSION CONVENT SCHOOL DAMODAR NAGAR KANPUR ROOM NO. 4"
  },
  {
    "partNumber": 251,
    "partName": "J S MISSION CONVENT SCHOOL DAMODAR NAGAR KANPUR ROOM NO. 5"
  },
  {
    "partNumber": 252,
    "partName": "J S MISSION CONVENT SCHOOL DAMODAR NAGAR KANPUR ROOM NO. 6"
  },
  {
    "partNumber": 253,
    "partName": "J S MISSION CONVENT SCHOOL DAMODAR NAGAR KANPUR ROOM NO. 7"
  },
  {
    "partNumber": 254,
    "partName": "COMPOSITE VIDAYLAYA KIDWAI NAGAR(NIKAT MUSICAL FOUNTAIN )  ROOM NO 1"
  },
  {
    "partNumber": 255,
    "partName": "COMPOSITE VIDAYLAYA KIDWAI NAGAR(NIKAT MUSICAL FOUNTAIN )  ROOM NO 2"
  },
  {
    "partNumber": 256,
    "partName": "COMPOSITE VIDAYLAYA KIDWAI NAGAR(NIKAT MUSICAL FOUNTAIN )  ROOM NO 3"
  },
  {
    "partNumber": 257,
    "partName": "COMPOSITE VIDAYLAYA KIDWAI NAGAR(NIKAT MUSICAL FOUNTAIN )  ROOM NO 4"
  },
  {
    "partNumber": 258,
    "partName": "COMPOSITE VIDAYLAYA KIDWAI NAGAR(NIKAT MUSICAL FOUNTAIN )  ROOM NO 5"
  },
  {
    "partNumber": 259,
    "partName": "DR. CHIRANJILAL RASHTRIYA  INTER COLLEGE  H BLOCK KIDWAI NAGAR ROOM NO 1"
  },
  {
    "partNumber": 260,
    "partName": "DR. CHIRANJILAL RASHTRIYA  INTER COLLEGE  H BLOCK KIDWAI NAGAR ROOM NO 2"
  },
  {
    "partNumber": 261,
    "partName": "DR. CHIRANJILAL RASHTRIYA  INTER COLLEGE  H BLOCK KIDWAI NAGAR ROOM NO 3"
  },
  {
    "partNumber": 262,
    "partName": "BRAHASPATI PARASNATAK MAHAVIDYALAY K BLOCK KIDWAI NAGAR ROOM NO 1"
  },
  {
    "partNumber": 263,
    "partName": "BRAHASPATI PARASNATAK MAHAVIDYALAY K BLOCK KIDWAI NAGAR ROOM NO 2"
  },
  {
    "partNumber": 264,
    "partName": "BRAHASPATI PARASNATAK MAHAVIDYALAY K BLOCK KIDWAI NAGAR ROOM NO 3"
  },
  {
    "partNumber": 265,
    "partName": "BRAHASPATI PARASNATAK MAHAVIDYALAY K BLOCK KIDWAI NAGAR ROOM NO 4"
  },
  {
    "partNumber": 266,
    "partName": "BRAHASPATI PARASNATAK MAHAVIDYALAY K BLOCK KIDWAI NAGAR ROOM NO 5"
  },
  {
    "partNumber": 267,
    "partName": "GHANSHYAMDAS SHIVKUMAR NAGRIK H. S. SCHOOL K BLOCK KIDWAI NAGAR ROOM NO 1"
  },
  {
    "partNumber": 268,
    "partName": "GHANSHYAMDAS SHIVKUMAR NAGRIK H. S. SCHOOL K BLOCK KIDWAI NAGAR ROOM NO 2"
  },
  {
    "partNumber": 269,
    "partName": "GHANSHYAMDAS SHIVKUMAR NAGRIK H. S. SCHOOL K BLOCK KIDWAI NAGAR ROOM NO 3"
  },
  {
    "partNumber": 270,
    "partName": "GHANSHYAMDAS SHIVKUMAR NAGRIK H. S. SCHOOL K BLOCK KIDWAI NAGAR ROOM NO 4"
  },
  {
    "partNumber": 271,
    "partName": "SHRIRAM PUBLIC SCHOOL Y BLOCK KIDWAI NAGAR ROOM NO 1"
  },
  {
    "partNumber": 272,
    "partName": "SHRIRAM PUBLIC SCHOOL Y BLOCK KIDWAI NAGAR ROOM NO 2"
  },
  {
    "partNumber": 273,
    "partName": "SHRIRAM PUBLIC SCHOOL Y BLOCK KIDWAI NAGAR ROOM NO 3"
  },
  {
    "partNumber": 274,
    "partName": "SHRIRAM PUBLIC SCHOOL Y BLOCK KIDWAI NAGAR ROOM NO 4"
  },
  {
    "partNumber": 275,
    "partName": "SHRIRAM PUBLIC SCHOOL Y BLOCK KIDWAI NAGAR ROOM NO 5"
  },
  {
    "partNumber": 276,
    "partName": "SHRIRAM PUBLIC SCHOOL Y BLOCK KIDWAI NAGAR ROOM NO 6"
  },
  {
    "partNumber": 277,
    "partName": "SHRIRAM PUBLIC SCHOOL Y BLOCK KIDWAI NAGAR ROOM NO 7"
  },
  {
    "partNumber": 278,
    "partName": "SHRIRAM PUBLIC SCHOOL Y BLOCK KIDWAI NAGAR ROOM NO 8"
  },
  {
    "partNumber": 279,
    "partName": "SHRIRAM PUBLIC SCHOOL Y BLOCK KIDWAI NAGAR ROOM NO 9"
  },
  {
    "partNumber": 280,
    "partName": "SHRIRAM PUBLIC SCHOOL Y BLOCK KIDWAI NAGAR ROOM NO 10"
  },
  {
    "partNumber": 281,
    "partName": "SHRIRAM PUBLIC SCHOOL Y BLOCK KIDWAI NAGAR ROOM NO 11"
  },
  {
    "partNumber": 282,
    "partName": "SHRI KIDWAI VIDHYALAYAH.INTER COLLAGE KIDWAI NAGAR ROOM NO.1"
  },
  {
    "partNumber": 283,
    "partName": "SHRI KIDWAI VIDHYALAYAH.INTER COLLAGE KIDWAI NAGAR ROOM NO.2"
  },
  {
    "partNumber": 284,
    "partName": "SHRI KIDWAI VIDHYALAYAH.INTER COLLAGE KIDWAI NAGAR ROOM NO.3"
  },
  {
    "partNumber": 285,
    "partName": "UP KIRANA SEVA  SAMITI VIDHYALAYA  SITE  NO. 1 KIDWAI NGAR ROOM NO 1"
  },
  {
    "partNumber": 286,
    "partName": "UP KIRANA SEVA  SAMITI VIDHYALAYA  SITE  NO. 1 KIDWAI NGAR ROOM NO 2"
  },
  {
    "partNumber": 287,
    "partName": "UP KIRANA SEVA  SAMITI VIDHYALAYA  SITE  NO. 1 KIDWAI NGAR ROOM NO 3"
  },
  {
    "partNumber": 288,
    "partName": "UP KIRANA SEVA  SAMITI VIDHYALAYA  SITE  NO. 1 KIDWAI NGAR ROOM NO 4"
  },
  {
    "partNumber": 289,
    "partName": "UP KIRANA SEVA  SAMITI VIDHYALAYA  SITE  NO. 1 KIDWAI NGAR ROOM NO 5"
  },
  {
    "partNumber": 290,
    "partName": "UP KIRANA SEVA  SAMITI VIDHYALAYA  SITE  NO. 1 KIDWAI NGAR ROOM NO 6"
  },
  {
    "partNumber": 291,
    "partName": "UP KIRANA SEVA  SAMITI VIDHYALAYA  SITE  NO. 1 KIDWAI NGAR ROOM NO 7"
  },
  {
    "partNumber": 292,
    "partName": "UP KIRANA SEVA  SAMITI VIDHYALAYA  SITE  NO. 1 KIDWAI NGAR ROOM NO 8"
  },
  {
    "partNumber": 293,
    "partName": "UP KIRANA SEVA  SAMITI VIDHYALAYA  SITE  NO. 1 KIDWAI NGAR ROOM NO 9"
  },
  {
    "partNumber": 294,
    "partName": "MODERN EDUCATION CENTER B BLOCK KIDWAI NAGAR ROOM NO 1"
  },
  {
    "partNumber": 295,
    "partName": "MODERN EDUCATION CENTER B BLOCK KIDWAI NAGAR ROOM NO 2"
  },
  {
    "partNumber": 296,
    "partName": "ANNAPURNA MEMORIAL JR. HIGH SCHOOL, CHHANGAMAL KA HATA JUHI ROOM NO 2"
  },
  {
    "partNumber": 297,
    "partName": "ANNAPURNA MEMORIAL JR. HIGH SCHOOL, CHHANGAMAL KA HATA JUHI ROOM NO 3"
  },
  {
    "partNumber": 298,
    "partName": "DR. SONE LAL PATEL SENIOR S. SCHOOL JUHI HAMIRPUR  RAOD ROOM NO 5"
  },
  {
    "partNumber": 299,
    "partName": "DR. SONE LAL PATEL SENIOR S. SCHOOL JUHI HAMIRPUR  RAOD ROOM NO 6"
  },
  {
    "partNumber": 300,
    "partName": "DR. SONE LAL PATEL SENIOR S. SCHOOL JUHI HAMIRPUR  RAOD ROOM NO 7"
  },
  {
    "partNumber": 301,
    "partName": "DR. SONE LAL PATEL SENIOR S. SCHOOL JUHI HAMIRPUR  RAOD ROOM NO 8"
  },
  {
    "partNumber": 302,
    "partName": "DR. SONE LAL PATEL SENIOR S. SCHOOL JUHI HAMIRPUR  RAOD ROOM NO 9"
  },
  {
    "partNumber": 303,
    "partName": "DR. SONE LAL PATEL SENIOR S. SCHOOL JUHI HAMIRPUR  RAOD ROOM NO 10"
  },
  {
    "partNumber": 304,
    "partName": "LALLU JUNIOR HIGH SCHOOL DHAKNAPURWA ROOM NO.1"
  },
  {
    "partNumber": 305,
    "partName": "LALLU JUNIOR HIGH SCHOOL DHAKNAPURWA ROOM NO.2"
  },
  {
    "partNumber": 306,
    "partName": "LALLU JUNIOR HIGH SCHOOL DHAKNAPURWA ROOM NO.3"
  },
  {
    "partNumber": 307,
    "partName": "LALLU JUNIOR HIGH SCHOOL DHAKNAPURWA ROOM NO.4"
  },
  {
    "partNumber": 308,
    "partName": "OXFORD MODEL CONVENT SCHOOL DHAKNAPURWA ROOM NO.1"
  },
  {
    "partNumber": 309,
    "partName": "OXFORD MODEL CONVENT SCHOOL DHAKNAPURWA ROOM NO.2"
  },
  {
    "partNumber": 310,
    "partName": "OMKAR NATH DHAWAN INTER COLLAGE ANANDPURI KIDWAI NAGAR ROOM NO.1"
  },
  {
    "partNumber": 311,
    "partName": "OMKAR NATH DHAWAN INTER COLLAGE ANANDPURI KIDWAI NAGAR ROOM NO.2"
  },
  {
    "partNumber": 312,
    "partName": "OMKAR NATH DHAWAN INTER COLLAGE ANANDPURI KIDWAI NAGAR ROOM NO.3"
  },
  {
    "partNumber": 313,
    "partName": "OMKAR NATH DHAWAN INTER COLLAGE ANANDPURI KIDWAI NAGAR ROOM NO.4"
  },
  {
    "partNumber": 314,
    "partName": "OMKAR NATH DHAWAN INTER COLLAGE ANANDPURI KIDWAI NAGAR ROOM NO.5"
  },
  {
    "partNumber": 315,
    "partName": "KANPUR GIRLS MAHAVIDYALAYA INTER COLLEGE KIDWAI NAGAR ROOM NO. 1"
  },
  {
    "partNumber": 316,
    "partName": "KANPUR GIRLS MAHAVIDYALAYA INTER COLLEGE KIDWAI NAGAR ROOM NO. 2"
  },
  {
    "partNumber": 317,
    "partName": "KANPUR GIRLS MAHAVIDYALAYA INTER COLLEGE KIDWAI NAGAR ROOM NO. 3"
  },
  {
    "partNumber": 318,
    "partName": "KANPUR GIRLS MAHAVIDYALAYA INTER COLLEGE KIDWAI NAGAR ROOM NO. 4"
  },
  {
    "partNumber": 319,
    "partName": "SARASWATI SHISHU MANDIR INTER COLLEGE O BLOCK, ANANDPURI ROOM NO. 1"
  },
  {
    "partNumber": 320,
    "partName": "SARASWATI SHISHU MANDIR INTER COLLEGE O BLOCK, ANANDPURI ROOM NO. 2"
  },
  {
    "partNumber": 321,
    "partName": "SARASWATI SHISHU MANDIR INTER COLLEGE O BLOCK, ANANDPURI ROOM NO. 3"
  },
  {
    "partNumber": 322,
    "partName": "SARASWATI SHISHU MANDIR INTER COLLEGE O BLOCK, ANANDPURI ROOM NO. 4"
  },
  {
    "partNumber": 323,
    "partName": "SARASWATI SHISHU MANDIR INTER COLLEGE O BLOCK, ANANDPURI ROOM NO. 5"
  },
  {
    "partNumber": 324,
    "partName": "SARASWATI SHISHU MANDIR INTER COLLEGE O BLOCK, ANANDPURI ROOM NO. 6"
  },
  {
    "partNumber": 325,
    "partName": "SHRI RATAN SHUKLA NAGAR NIGAM INTER  COLLEGE JUHI KHURD PARAMPURWAROOM NO 1"
  },
  {
    "partNumber": 326,
    "partName": "SHRI RATAN SHUKLA NAGAR NIGAM INTER  COLLEGE JUHI KHURD PARAMPURWAROOM NO 2"
  },
  {
    "partNumber": 327,
    "partName": "SHRI RATAN SHUKLA NAGAR NIGAM INTER  COLLEGE JUHI KHURD PARAMPURWAROOM NO 3"
  },
  {
    "partNumber": 328,
    "partName": "SHRI RATAN SHUKLA NAGAR NIGAM INTER  COLLEGE COLLEGE JUHI KHURD PARAMPURWAROOM NO 4"
  },
  {
    "partNumber": 329,
    "partName": "SHRI RATAN SHUKLA NAGAR NIGAM INTER  COLLEGE JUHI KHURD PARAMPURWAROOM NO 5"
  },
  {
    "partNumber": 330,
    "partName": "SHRI RATAN SHUKLA NAGAR NIGAM INTER  COLLEGE JUHI KHURD PARAMPURWAROOM NO 6"
  },
  {
    "partNumber": 331,
    "partName": "MODERN SUPER NATIONAL VIDYALAYA BASANTI NAGAR ROOM NO 1"
  },
  {
    "partNumber": 332,
    "partName": "MODERN SUPER NATIONAL VIDYALAYA BASANTI NAGAR ROOM NO 2"
  },
  {
    "partNumber": 333,
    "partName": "CAMBRIDGE CONVENT SCHOOL JUHI PARAMPURWA ROOM NO 1"
  },
  {
    "partNumber": 334,
    "partName": "CAMBRIDGE CONVENT SCHOOL JUHI PARAMPURWA ROOM NO 2"
  },
  {
    "partNumber": 335,
    "partName": "CAMBRIDGE CONVENT SCHOOL JUHI PARAMPURWA ROOM NO 3"
  },
  {
    "partNumber": 336,
    "partName": "CAMBRIDGE CONVENT SCHOOL JUHI PARAMPURWA ROOM NO 4"
  },
  {
    "partNumber": 337,
    "partName": "MODERN SUPER NATIONAL VIDYALAYA BASANTI NAGAR ROOM NO 3"
  },
  {
    "partNumber": 338,
    "partName": "SAMRAT ASHOK VIDYA UDYAN SCHOOL JALPA NAGAR ROOM 1"
  },
  {
    "partNumber": 339,
    "partName": "SAMRAT ASHOK VIDYA UDYAN SCHOOL JALPA NAGAR ROOM 2"
  },
  {
    "partNumber": 340,
    "partName": "SAMRAT ASHOK VIDYA UDYAN SCHOOL JALPA NAGAR ROOM 3"
  },
  {
    "partNumber": 341,
    "partName": "NAGAR NIGAM GILRS U. MA.V. BASANTI NAGAR JUHI KANPUR ROOM NO 1"
  },
  {
    "partNumber": 342,
    "partName": "NAGAR NIGAM GILRS U. MA.V. BASANTI NAGAR JUHI KANPUR ROOM NO 2"
  },
  {
    "partNumber": 343,
    "partName": "NAGAR NIGAM GILRS U. MA.V. BASANTI NAGAR JUHI KANPUR ROOM NO 3"
  },
  {
    "partNumber": 344,
    "partName": "NAGAR NIGAM GILRS U. MA.V. BASANTI NAGAR JUHI KANPUR ROOM NO 4"
  },
  {
    "partNumber": 345,
    "partName": "COMPOSITE VIDAYLAYA KANYA JUHI ROOM NO 1"
  },
  {
    "partNumber": 346,
    "partName": "COMPOSITE VIDAYLAYA KANYA JUHI ROOM NO 2"
  },
  {
    "partNumber": 347,
    "partName": "COMPOSITE VIDAYLAYA KANYA JUHI ROOM NO 3"
  },
  {
    "partNumber": 348,
    "partName": "COMPOSITE VIDAYLAYA KANYA JUHI ROOM NO 4"
  },
  {
    "partNumber": 349,
    "partName": "COMPOSITE VIDAYLAYA KANYA JUHI ROOM NO 5"
  },
  {
    "partNumber": 350,
    "partName": "COMPOSITE VIDAYLAYA KANYA JUHI ROOM NO 6"
  }
]