[
  {
    "partNumber": 1,
    "partName": "PS RAJAURA NORTH"
  },
  {
    "partNumber": 2,
    "partName": "PS RAJAURA SOUTH"
  },
  {
    "partNumber": 3,
    "partName": "PS JALALPUR BHAGGU ROOM NO 1"
  },
  {
    "partNumber": 4,
    "partName": "PS JALALPUR BHAGGU ROOM NO 2"
  },
  {
    "partNumber": 5,
    "partName": "PS MAURAWAN"
  },
  {
    "partNumber": 6,
    "partName": "PS DEHARIYAWAN NORTH"
  },
  {
    "partNumber": 7,
    "partName": "PS DEHARIYAWAN SOUTH"
  },
  {
    "partNumber": 8,
    "partName": "CS PURE NANDA ASKARANPUR ROOM NO-1"
  },
  {
    "partNumber": 9,
    "partName": "CS PURE NANDA ASKARANPUR ROOM NO-2"
  },
  {
    "partNumber": 10,
    "partName": "CS  PURE NANDA ASKARANPUR ROOM NO-3"
  },
  {
    "partNumber": 11,
    "partName": "PS SAHAJPUR"
  },
  {
    "partNumber": 12,
    "partName": "CS BANKAT NORTH"
  },
  {
    "partNumber": 13,
    "partName": "CS BANKAT SOUTH"
  },
  {
    "partNumber": 14,
    "partName": "KANYA PS MARUE SAHAISINGH NORTH"
  },
  {
    "partNumber": 15,
    "partName": "KANYA PS MARUE SAHAISINGH SOUTH"
  },
  {
    "partNumber": 16,
    "partName": "PS SAFIPUR"
  },
  {
    "partNumber": 17,
    "partName": "PS GEENJA"
  },
  {
    "partNumber": 18,
    "partName": "HPS DAYALJOT"
  },
  {
    "partNumber": 19,
    "partName": "CS MOHAMMADPUR"
  },
  {
    "partNumber": 20,
    "partName": "KANYA PS DEVAPUR"
  },
  {
    "partNumber": 21,
    "partName": "K. K. A. D. INTER COLLEGE MAZRUDDINPUR EAST"
  },
  {
    "partNumber": 22,
    "partName": "K. K. A. D. INTER COLLEGE MAZRUDDINPUR WEST"
  },
  {
    "partNumber": 23,
    "partName": "K. K. A. D. INTER COLLEGE MAZRUDDINPUR EXTRA ROOM"
  },
  {
    "partNumber": 24,
    "partName": "PS TAJPUR"
  },
  {
    "partNumber": 25,
    "partName": "CS KONCCHA NORTH"
  },
  {
    "partNumber": 26,
    "partName": "CS KONCCHA SOUTH"
  },
  {
    "partNumber": 27,
    "partName": "CS KONCCHA CENTER"
  },
  {
    "partNumber": 28,
    "partName": "CS KONCCHA EXTRA ROOM"
  },
  {
    "partNumber": 29,
    "partName": "PS SONVERSA MUSALMEEN ROOM NO 1"
  },
  {
    "partNumber": 30,
    "partName": "PS SONVERSA MUSALMEEN ROOM NO 2"
  },
  {
    "partNumber": 31,
    "partName": "PS KODRA MUSALMEEN"
  },
  {
    "partNumber": 32,
    "partName": "PS MUMARIJNAGAR"
  },
  {
    "partNumber": 33,
    "partName": "PS AMAWAN"
  },
  {
    "partNumber": 34,
    "partName": "PS SARAIKHARGI"
  },
  {
    "partNumber": 35,
    "partName": "PS MAHMADBHARI"
  },
  {
    "partNumber": 36,
    "partName": "PS PURE GULJAAR ROOM NO 1"
  },
  {
    "partNumber": 37,
    "partName": "PS PURE GULJAAR ROOM NO 2"
  },
  {
    "partNumber": 38,
    "partName": "PS ASREWA ROOM NO 1"
  },
  {
    "partNumber": 39,
    "partName": "PS ASREWA ROOM NO 2"
  },
  {
    "partNumber": 40,
    "partName": "PS ASREWA ROOM NO 3"
  },
  {
    "partNumber": 41,
    "partName": "PS HARVANSHPUR"
  },
  {
    "partNumber": 42,
    "partName": "CS MANGARI ROOM NO 1"
  },
  {
    "partNumber": 43,
    "partName": "CS MANGARI ROOM NO 2"
  },
  {
    "partNumber": 44,
    "partName": "PS RAMNAGAR WEST"
  },
  {
    "partNumber": 45,
    "partName": "PS RAMNAGAR EAST"
  },
  {
    "partNumber": 46,
    "partName": "PS NUWAWA BAIDRA ROOM NO 1"
  },
  {
    "partNumber": 47,
    "partName": "PS NUWAWA BAIDRA ROOM NO 2"
  },
  {
    "partNumber": 48,
    "partName": "CS BHAIROPUR TIKRA NORTH"
  },
  {
    "partNumber": 49,
    "partName": "CS BHAIROPUR TIKRA SOUTH"
  },
  {
    "partNumber": 50,
    "partName": "PS BODAHRI"
  },
  {
    "partNumber": 51,
    "partName": "PS KORO RAGHAVPUR EAST"
  },
  {
    "partNumber": 52,
    "partName": "PS KORO RAGHAVPUR WEST"
  },
  {
    "partNumber": 53,
    "partName": "PS KORO RAGHAVPUR EXTRA ROOM"
  },
  {
    "partNumber": 54,
    "partName": "PS MAU"
  },
  {
    "partNumber": 55,
    "partName": "PS RAMPUR AHIRAULI ROOM NO 1"
  },
  {
    "partNumber": 56,
    "partName": "PS RAMPUR AHIRAULI ROOM NO 2"
  },
  {
    "partNumber": 57,
    "partName": "SAHEED JAGDAMBA PRASAD CS BENIGADDOPUR NORTH"
  },
  {
    "partNumber": 58,
    "partName": "SAHEED JAGDAMBA PRASAD CS BENIGADDOPUR SOUTH"
  },
  {
    "partNumber": 59,
    "partName": "SAHEED JAGDAMBA PRASAD CS BENIGADDOPUR EXTRA ROOM"
  },
  {
    "partNumber": 60,
    "partName": "PS RASOOLPUR BARAOLI"
  },
  {
    "partNumber": 61,
    "partName": "PS PRATAPPUR URF BARHUPUR"
  },
  {
    "partNumber": 62,
    "partName": "PS KHIDDIRPUR EAST"
  },
  {
    "partNumber": 63,
    "partName": "PS KHIDDIRPUR EXTRA ROOM"
  },
  {
    "partNumber": 64,
    "partName": "PS KHIDDIRPUR WEST"
  },
  {
    "partNumber": 65,
    "partName": "PS PAROMA EAST"
  },
  {
    "partNumber": 66,
    "partName": "PS PAROMA WEST"
  },
  {
    "partNumber": 67,
    "partName": "PS SALHIPUR EAST"
  },
  {
    "partNumber": 68,
    "partName": "PS SALHIPUR WEST"
  },
  {
    "partNumber": 69,
    "partName": "PS SALHIPUR EXTRA ROOM"
  },
  {
    "partNumber": 70,
    "partName": "PS PARSUHI ROOM NO 1"
  },
  {
    "partNumber": 71,
    "partName": "PS PARSUHI ROOM NO 2"
  },
  {
    "partNumber": 72,
    "partName": "PS LAKSHMANPUR GRANT"
  },
  {
    "partNumber": 73,
    "partName": "JHS JASARPUR NORTH"
  },
  {
    "partNumber": 74,
    "partName": "JHS JASARPUR SOUTH"
  },
  {
    "partNumber": 75,
    "partName": "JHS JASARPUR EXTRA ROOM"
  },
  {
    "partNumber": 76,
    "partName": "PS JOHAN NORTH"
  },
  {
    "partNumber": 77,
    "partName": "PS JOHAN SOUTH"
  },
  {
    "partNumber": 78,
    "partName": "PS JOHAN EXTRA ROOM"
  },
  {
    "partNumber": 79,
    "partName": "PS KHETPALIYA"
  },
  {
    "partNumber": 80,
    "partName": "PS NANDAUNA"
  },
  {
    "partNumber": 81,
    "partName": "PS SANKARPUR"
  },
  {
    "partNumber": 82,
    "partName": "PS SANKARPUR EXTRA ROOM"
  },
  {
    "partNumber": 83,
    "partName": "PS KANAVA"
  },
  {
    "partNumber": 84,
    "partName": "PS GANGAPUR MO. RAMAUPUR"
  },
  {
    "partNumber": 85,
    "partName": "PS BHULAIPUR NIDHIYAWA"
  },
  {
    "partNumber": 86,
    "partName": "CS BENIPUR"
  },
  {
    "partNumber": 87,
    "partName": "CS BHARHUKHATA"
  },
  {
    "partNumber": 88,
    "partName": "PS BHARHUKHATA"
  },
  {
    "partNumber": 89,
    "partName": "PS CHAURE CHANDAULI NORTH"
  },
  {
    "partNumber": 90,
    "partName": "PS CHAURE CHANDAULI SOUTH"
  },
  {
    "partNumber": 91,
    "partName": "PS CHAURE CHANDAULI EXTRA ROOM"
  },
  {
    "partNumber": 92,
    "partName": "PS RNDAULI PACHCHIM PALI ROOM NO 1"
  },
  {
    "partNumber": 93,
    "partName": "PS RNDAULI PACHCHIM PALI ROOM NO 2"
  },
  {
    "partNumber": 94,
    "partName": "PS MANJHA SONAURA"
  },
  {
    "partNumber": 95,
    "partName": "PS AHIRANI GOPALPUR"
  },
  {
    "partNumber": 96,
    "partName": "CS BAITIKALA NORTH"
  },
  {
    "partNumber": 97,
    "partName": "CS BAITIKALA EXTRA ROOM"
  },
  {
    "partNumber": 98,
    "partName": "CS BAITIKALA SOUTH"
  },
  {
    "partNumber": 99,
    "partName": "CS BAITIKALA WEST"
  },
  {
    "partNumber": 100,
    "partName": "JHS RASULPUR AMMO"
  },
  {
    "partNumber": 101,
    "partName": "PS NUNAPURAB"
  },
  {
    "partNumber": 102,
    "partName": "CS RAUHARI NORTH"
  },
  {
    "partNumber": 103,
    "partName": "CS RAUHARI SOUTH"
  },
  {
    "partNumber": 104,
    "partName": "PS SIHORIA"
  },
  {
    "partNumber": 105,
    "partName": "PS GOTHAURA"
  },
  {
    "partNumber": 106,
    "partName": "PS PALIPURAB"
  },
  {
    "partNumber": 107,
    "partName": "PS HATHIGO SOUTH"
  },
  {
    "partNumber": 108,
    "partName": "PS HATHIGO NORTH"
  },
  {
    "partNumber": 109,
    "partName": "PS HATHIGO EXTRA ROOM NO 1"
  },
  {
    "partNumber": 110,
    "partName": "PS HATHIGO EXTRA ROOM NO 2"
  },
  {
    "partNumber": 111,
    "partName": "PS JAJWARA EAST"
  },
  {
    "partNumber": 112,
    "partName": "PS JAJWARA WEST"
  },
  {
    "partNumber": 113,
    "partName": "PS BAISUPALI"
  },
  {
    "partNumber": 114,
    "partName": "CS PARAHATHIGO"
  },
  {
    "partNumber": 115,
    "partName": "PS ARSATH"
  },
  {
    "partNumber": 116,
    "partName": "JHS ARIYASI"
  },
  {
    "partNumber": 117,
    "partName": "PS ARIYASI"
  },
  {
    "partNumber": 118,
    "partName": "PS RAMPUR PRATAP ROOM NO. 1"
  },
  {
    "partNumber": 119,
    "partName": "PS RAMPUR PRATAP ROOM NO. 2"
  },
  {
    "partNumber": 120,
    "partName": "CS GARAULI"
  },
  {
    "partNumber": 121,
    "partName": "PS PANCHGAWA"
  },
  {
    "partNumber": 122,
    "partName": "PANCHAYAT BHAWAN DHAMHAR ROOM NO 1"
  },
  {
    "partNumber": 123,
    "partName": "PANCHAYAT BHAWAN DHAMHAR ROOM NO 2"
  },
  {
    "partNumber": 124,
    "partName": "JHS HAIDARGANJ ROOM NO 1"
  },
  {
    "partNumber": 125,
    "partName": "JHS HAIDARGANJ ROOM NO 2"
  },
  {
    "partNumber": 126,
    "partName": "CS GAUHANIKHURD EAST"
  },
  {
    "partNumber": 127,
    "partName": "CS GAUHANIKHURD WEST"
  },
  {
    "partNumber": 128,
    "partName": "JHS RAMWAKALA"
  },
  {
    "partNumber": 129,
    "partName": "PS PARARAM NORTH"
  },
  {
    "partNumber": 130,
    "partName": "PS PARARAM SOUTH"
  },
  {
    "partNumber": 131,
    "partName": "CS THARIYAKALA ROOM NO 1"
  },
  {
    "partNumber": 132,
    "partName": "CS THARIYAKALA ROOM NO 2"
  },
  {
    "partNumber": 133,
    "partName": "CS THARIYAKALA EXTRA ROOM"
  },
  {
    "partNumber": 134,
    "partName": "PS ANKARI"
  },
  {
    "partNumber": 135,
    "partName": "PS PACHIYANA"
  },
  {
    "partNumber": 136,
    "partName": "PS GAURA NORTH"
  },
  {
    "partNumber": 137,
    "partName": "PS GAURA SOUTH"
  },
  {
    "partNumber": 138,
    "partName": "PS GAURA EXTRA ROOM"
  },
  {
    "partNumber": 139,
    "partName": "SHRI ANANT INTER COLLAGE KHAPARADEEH NORTH"
  },
  {
    "partNumber": 140,
    "partName": "SHRI ANANT INTER COLLAGE KHAPARADEEH SOUTH"
  },
  {
    "partNumber": 141,
    "partName": "PS KATAUNA"
  },
  {
    "partNumber": 142,
    "partName": "PS HAIDERGANJ 1 EAST"
  },
  {
    "partNumber": 143,
    "partName": "PS HAIDERGANJ 1 WEST"
  },
  {
    "partNumber": 144,
    "partName": "PS HAIDERGANJ 1 NEW EAST"
  },
  {
    "partNumber": 145,
    "partName": "PS HAIDERGANJ 1 NEW WEST"
  },
  {
    "partNumber": 146,
    "partName": "PS JANA BAZAR ROOM NO 1"
  },
  {
    "partNumber": 147,
    "partName": "PS JANA BAZAR ROOM NO 2"
  },
  {
    "partNumber": 148,
    "partName": "PS JANA BAZAR ROOM NO 3"
  },
  {
    "partNumber": 149,
    "partName": "PS JANA BAZAR ROOM NO 4"
  },
  {
    "partNumber": 150,
    "partName": "PS KHAJURIPUR"
  },
  {
    "partNumber": 151,
    "partName": "PS SAHSIPUR"
  },
  {
    "partNumber": 152,
    "partName": "PS BELGARA NORTH"
  },
  {
    "partNumber": 153,
    "partName": "PS BELGARA SOUTH"
  },
  {
    "partNumber": 154,
    "partName": "CS TAKMINGANJ EAST"
  },
  {
    "partNumber": 155,
    "partName": "CS TAKMINGANJ WEST"
  },
  {
    "partNumber": 156,
    "partName": "PS DHARMPUR"
  },
  {
    "partNumber": 157,
    "partName": "PS BARA"
  },
  {
    "partNumber": 158,
    "partName": "PS KAKRAHI"
  },
  {
    "partNumber": 159,
    "partName": "PS CHARAWA ROOM NO 1"
  },
  {
    "partNumber": 160,
    "partName": "PS CHARAWA ROOM NO 2"
  },
  {
    "partNumber": 161,
    "partName": "CS SAMDA"
  },
  {
    "partNumber": 162,
    "partName": "CS BARANW NORTH"
  },
  {
    "partNumber": 163,
    "partName": "CS BARANW EXTRA ROOM"
  },
  {
    "partNumber": 164,
    "partName": "CS BARAWN WEST"
  },
  {
    "partNumber": 165,
    "partName": "PS UNCHGAON"
  },
  {
    "partNumber": 166,
    "partName": "CS NETWARI CHATURPUR ROOM NO. 1"
  },
  {
    "partNumber": 167,
    "partName": "CS NETWARI CHATURPUR ROOM NO. 2"
  },
  {
    "partNumber": 168,
    "partName": "PS PARAGRIBASHAH EAST"
  },
  {
    "partNumber": 169,
    "partName": "PS PARAGRIBASHAH WEST"
  },
  {
    "partNumber": 170,
    "partName": "PS FAKHARPUR"
  },
  {
    "partNumber": 171,
    "partName": "CS KESHARUWA BUJURG NORTH"
  },
  {
    "partNumber": 172,
    "partName": "CS KESHARUWA BUJURG SOUTH"
  },
  {
    "partNumber": 173,
    "partName": "PS MAAHANMAU"
  },
  {
    "partNumber": 174,
    "partName": "CS PARSAWAN MAHOLA EAST"
  },
  {
    "partNumber": 175,
    "partName": "CS PARSAWAN MAHOLA WEST"
  },
  {
    "partNumber": 176,
    "partName": "CS PARSAWAN MAHOLA EXTRA ROOM"
  },
  {
    "partNumber": 177,
    "partName": "CS DANDUPUR"
  },
  {
    "partNumber": 178,
    "partName": "PS VIJAYANPUR SAJAHARA EAST"
  },
  {
    "partNumber": 179,
    "partName": "PS VIJAYANPUR SAJAHARA WEST"
  },
  {
    "partNumber": 180,
    "partName": "PS NAGPALI"
  },
  {
    "partNumber": 181,
    "partName": "PS KANAKPUR JHAGRAULI ROOM NO 1"
  },
  {
    "partNumber": 182,
    "partName": "PS KANAKPUR JHAGRAULI ROOM NO 2"
  },
  {
    "partNumber": 183,
    "partName": "PS MIJHAULI KISUNDASPUR"
  },
  {
    "partNumber": 184,
    "partName": "CS CHAKRASENPUR"
  },
  {
    "partNumber": 185,
    "partName": "PS RAMDASPUR"
  },
  {
    "partNumber": 186,
    "partName": "PS TARDEEH EAST"
  },
  {
    "partNumber": 187,
    "partName": "PS TARDEEH WEST"
  },
  {
    "partNumber": 188,
    "partName": "JHS GAYASPUR NORTH"
  },
  {
    "partNumber": 189,
    "partName": "JHS GAYASPUR EXTRA ROOM"
  },
  {
    "partNumber": 190,
    "partName": "JHS GAYASPUR SOUTH"
  },
  {
    "partNumber": 191,
    "partName": "PS GAURA"
  },
  {
    "partNumber": 192,
    "partName": "KISAN INTER COLLAGE BANKATA EAST"
  },
  {
    "partNumber": 193,
    "partName": "KISAN INTER COLLAGE BANKATA WEST"
  },
  {
    "partNumber": 194,
    "partName": "PS MATHIYA"
  },
  {
    "partNumber": 195,
    "partName": "PS CHANDPUR"
  },
  {
    "partNumber": 196,
    "partName": "PS GHURITIKAR NORTH"
  },
  {
    "partNumber": 197,
    "partName": "PS GHURITIKAR SOUTH"
  },
  {
    "partNumber": 198,
    "partName": "PS KHEMIPUR NIDHIYAWA EAST"
  },
  {
    "partNumber": 199,
    "partName": "PS KHEMIPUR NIDHIYAWA WEST"
  },
  {
    "partNumber": 200,
    "partName": "CS KAKOLI NORTH"
  },
  {
    "partNumber": 201,
    "partName": "CS KAKOLI SOUTH"
  },
  {
    "partNumber": 202,
    "partName": "PS BAHARPUR"
  },
  {
    "partNumber": 203,
    "partName": "PS PURUSHOTTAMPUR"
  },
  {
    "partNumber": 204,
    "partName": "PS BALAPUR"
  },
  {
    "partNumber": 205,
    "partName": "JANTA INTER COLLAGE JAISINGHMAU ROOM NO.-1"
  },
  {
    "partNumber": 206,
    "partName": "JANTA INTER COLLAGE JAISINGHMAU ROOM NO.-2"
  },
  {
    "partNumber": 207,
    "partName": "PS NASRATPUR ROON NO 1"
  },
  {
    "partNumber": 208,
    "partName": "PS NASRATPUR ROON NO 2"
  },
  {
    "partNumber": 209,
    "partName": "PS DARIYAPUR ROOM NO 1"
  },
  {
    "partNumber": 210,
    "partName": "PS DARIYAPUR ROOM NO 2"
  },
  {
    "partNumber": 211,
    "partName": "CS DAUDAHA"
  },
  {
    "partNumber": 212,
    "partName": "PS SARAISAGAR"
  },
  {
    "partNumber": 213,
    "partName": "PS AGAGANJ ROOM NO 1"
  },
  {
    "partNumber": 214,
    "partName": "PS AGAGANJ ROOM NO 2"
  },
  {
    "partNumber": 215,
    "partName": "CS BALLIKRIPAL PUR"
  },
  {
    "partNumber": 216,
    "partName": "CS TARUN NORTH"
  },
  {
    "partNumber": 217,
    "partName": "CS TARUN NORTH EXTRA ROOM"
  },
  {
    "partNumber": 218,
    "partName": "CS TARUN SOUTH"
  },
  {
    "partNumber": 219,
    "partName": "PS NARAYANPUR"
  },
  {
    "partNumber": 220,
    "partName": "PS KICHHUTI KISHUNDASPUR"
  },
  {
    "partNumber": 221,
    "partName": "CS SONOURAGAUPUR EAST"
  },
  {
    "partNumber": 222,
    "partName": "CS SONOURAGAUPUR WEST"
  },
  {
    "partNumber": 223,
    "partName": "CS SONAURAGAUPUR EXTRA ROOM"
  },
  {
    "partNumber": 224,
    "partName": "PS FATEHPUR KAMASIN EAST"
  },
  {
    "partNumber": 225,
    "partName": "PS FATEHPUR KAMASIN WEST"
  },
  {
    "partNumber": 226,
    "partName": "PS FATEHPUR KAMSIN EXTRA ROOM"
  },
  {
    "partNumber": 227,
    "partName": "SARDAR BALLABH BHAI PATEL JHSKARNAIPUR MU0 PARAGARIBSHAH"
  },
  {
    "partNumber": 228,
    "partName": "PS BIBIPUR, PEDRA"
  },
  {
    "partNumber": 229,
    "partName": "PS YADAVPUR"
  },
  {
    "partNumber": 230,
    "partName": "CS BHADAAR NORTH"
  },
  {
    "partNumber": 231,
    "partName": "CS BHADAAR SOUTH"
  },
  {
    "partNumber": 232,
    "partName": "PS KELALAL KHAN NORTH"
  },
  {
    "partNumber": 233,
    "partName": "PS KELALAL KHAN SOUTH"
  },
  {
    "partNumber": 234,
    "partName": "PS MAIHARKABEER PUR"
  },
  {
    "partNumber": 235,
    "partName": "EM PS IMILIYA ROOM NO 1"
  },
  {
    "partNumber": 236,
    "partName": "EM PS IMILIYA ROOM NO 2"
  },
  {
    "partNumber": 237,
    "partName": "GGIC SARAIMANODHAR ROOM NO. 1"
  },
  {
    "partNumber": 238,
    "partName": "GGIC SARAIMANODHAR ROOM NO. 2"
  },
  {
    "partNumber": 239,
    "partName": "CS SIHIPUR ROOM NO 1"
  },
  {
    "partNumber": 240,
    "partName": "CS SIHIPUR ROOM NO 2"
  },
  {
    "partNumber": 241,
    "partName": "CS SIHIPUR EXTRA ROOM"
  },
  {
    "partNumber": 242,
    "partName": "PS BELA NORTH"
  },
  {
    "partNumber": 243,
    "partName": "PS BELA SOUTH"
  },
  {
    "partNumber": 244,
    "partName": "CS BHOPADUHIYA NORTH"
  },
  {
    "partNumber": 245,
    "partName": "CS BHOPADUHIYA SOUTH"
  },
  {
    "partNumber": 246,
    "partName": "CS RAKHAUNA"
  },
  {
    "partNumber": 247,
    "partName": "PS NAGAIPUR"
  },
  {
    "partNumber": 248,
    "partName": "PS KUWANDAND"
  },
  {
    "partNumber": 249,
    "partName": "CS KARAUNDI"
  },
  {
    "partNumber": 250,
    "partName": "PS MALAWAN ROOM NO 1"
  },
  {
    "partNumber": 251,
    "partName": "PS MALAWAN ROOM NO 2"
  },
  {
    "partNumber": 252,
    "partName": "PS KARNAIPUR"
  },
  {
    "partNumber": 253,
    "partName": "PS DOSTGRAMPUR"
  },
  {
    "partNumber": 254,
    "partName": "PS SIRSA"
  },
  {
    "partNumber": 255,
    "partName": "PS ODIRATNATHPUR"
  },
  {
    "partNumber": 256,
    "partName": "PS HUSAINPUR ROOM NO 1"
  },
  {
    "partNumber": 257,
    "partName": "PS HUSAINPUR ROOM NO 2"
  },
  {
    "partNumber": 258,
    "partName": "PS DHAURAHRAKUTI"
  },
  {
    "partNumber": 259,
    "partName": "JHS NANSA"
  },
  {
    "partNumber": 260,
    "partName": "PS GOPALPUR"
  },
  {
    "partNumber": 261,
    "partName": "PS PALIACHALPUR EAST"
  },
  {
    "partNumber": 262,
    "partName": "PS PALIACHALPUR WEST"
  },
  {
    "partNumber": 263,
    "partName": "PS PALIACHALPUR EXTRA ROOM"
  },
  {
    "partNumber": 264,
    "partName": "PS CHITAWAN NORTH"
  },
  {
    "partNumber": 265,
    "partName": "PS CHITAWAN SOUTH"
  },
  {
    "partNumber": 266,
    "partName": "JHS BAREHTA ROOM NO-1"
  },
  {
    "partNumber": 267,
    "partName": "JHS BAREHTA ROOM NO-2"
  },
  {
    "partNumber": 268,
    "partName": "PS RAJAURA"
  },
  {
    "partNumber": 269,
    "partName": "PS BEDAPUR"
  },
  {
    "partNumber": 270,
    "partName": "PS PICHHAURA"
  },
  {
    "partNumber": 271,
    "partName": "PS TIKRI NORTH"
  },
  {
    "partNumber": 272,
    "partName": "PS TIKRI SOUTH"
  },
  {
    "partNumber": 273,
    "partName": "CS TARAPUR"
  },
  {
    "partNumber": 274,
    "partName": "PS GURAULI"
  },
  {
    "partNumber": 275,
    "partName": "CS CHACHIKPUR"
  },
  {
    "partNumber": 276,
    "partName": "JHS KUMHIYA NORTH"
  },
  {
    "partNumber": 277,
    "partName": "JHS KUMHIYA SOUTH"
  },
  {
    "partNumber": 278,
    "partName": "PS BHOYA EXTRA ROOM"
  },
  {
    "partNumber": 279,
    "partName": "PS AMAUNI"
  },
  {
    "partNumber": 280,
    "partName": "PS MAHRAJIPUR"
  },
  {
    "partNumber": 281,
    "partName": "JAI KISAN INTER COLLEGE ARWAT"
  },
  {
    "partNumber": 282,
    "partName": "PS JAGDISHPUR"
  },
  {
    "partNumber": 283,
    "partName": "PS SINHORIYA"
  },
  {
    "partNumber": 284,
    "partName": "PS MEDNIPUR"
  },
  {
    "partNumber": 285,
    "partName": "PS HAIDERPUR"
  },
  {
    "partNumber": 286,
    "partName": "PS KALYANPUR BRAULI NORTH"
  },
  {
    "partNumber": 287,
    "partName": "PS KALYANPUR BARAULI SOUTH"
  },
  {
    "partNumber": 288,
    "partName": "PS RAUVA LOHANGPUR PRATHAM KACHHA"
  },
  {
    "partNumber": 289,
    "partName": "PS RAUVA LOHANGPUR SECOND"
  },
  {
    "partNumber": 290,
    "partName": "CS PAMPARPUR"
  },
  {
    "partNumber": 291,
    "partName": "CS BIKAPUR"
  },
  {
    "partNumber": 292,
    "partName": "CS BENIYA"
  },
  {
    "partNumber": 293,
    "partName": "PS RAMPUR BUJURG"
  },
  {
    "partNumber": 294,
    "partName": "BABA DOODHNATH L.M.V. NEVKABIR PUR"
  },
  {
    "partNumber": 295,
    "partName": "PS PARSAULI MAJRE ALNABHARI EAST"
  },
  {
    "partNumber": 296,
    "partName": "PS PARSAULI MAJRE ALNABHARI WEST"
  },
  {
    "partNumber": 297,
    "partName": "PS MUJBHARIYA (KESHAVPUR)"
  },
  {
    "partNumber": 298,
    "partName": "CS BERASPUR"
  },
  {
    "partNumber": 299,
    "partName": "CS DURGAPUR RAMPURVA"
  },
  {
    "partNumber": 300,
    "partName": "PS SARANGPUR"
  },
  {
    "partNumber": 301,
    "partName": "CS TARGAUHAN"
  },
  {
    "partNumber": 302,
    "partName": "PS CHHATARA"
  },
  {
    "partNumber": 303,
    "partName": "PS BARAIPARA"
  },
  {
    "partNumber": 304,
    "partName": "CS DAMODERPUR"
  },
  {
    "partNumber": 305,
    "partName": "PANCHAYAT BHAWAN MAIN HALL KAJIPUR VISHVA UPARHAR"
  },
  {
    "partNumber": 306,
    "partName": "PS KAJIPUR RAKURA"
  },
  {
    "partNumber": 307,
    "partName": "CS NAKATWARA"
  },
  {
    "partNumber": 308,
    "partName": "CS RAMPUR PUWARI"
  },
  {
    "partNumber": 309,
    "partName": "PS RAMPUR PUWARI MANJHA SECOND"
  },
  {
    "partNumber": 310,
    "partName": "PS KAJIPUR MANJHA EAST"
  },
  {
    "partNumber": 311,
    "partName": "PS ISHASARAI"
  },
  {
    "partNumber": 312,
    "partName": "CS DALPATPUR ROOM NO-1"
  },
  {
    "partNumber": 313,
    "partName": "CS DALPATPUR ROOM NO-2"
  },
  {
    "partNumber": 314,
    "partName": "CS DALPATPUR ROOM NO-3"
  },
  {
    "partNumber": 315,
    "partName": "CS DALPATPUR ROOM NO-4"
  },
  {
    "partNumber": 316,
    "partName": "PS AALAPUR EAST"
  },
  {
    "partNumber": 317,
    "partName": "PS AALAPUR WEST"
  },
  {
    "partNumber": 318,
    "partName": "PS RAGHUNATHPUR"
  },
  {
    "partNumber": 319,
    "partName": "PANCHAYAT BHAWAN JARAHI ROOM NUMBER 1"
  },
  {
    "partNumber": 320,
    "partName": "PANCHAYAT BHAWAN JARAHI ROOM NUMBER 2"
  },
  {
    "partNumber": 321,
    "partName": "CS JARAHI"
  },
  {
    "partNumber": 322,
    "partName": "PS DEVASURYABHAN PUR"
  },
  {
    "partNumber": 323,
    "partName": "CS BABUAPUR"
  },
  {
    "partNumber": 324,
    "partName": "PS JAJVAT"
  },
  {
    "partNumber": 325,
    "partName": "PS MAYA BHIKHI NORTH"
  },
  {
    "partNumber": 326,
    "partName": "PS MAYA BHIKHI SOUTH"
  },
  {
    "partNumber": 327,
    "partName": "PS RATANPUR"
  },
  {
    "partNumber": 328,
    "partName": "PS KANAKPUR NORTH"
  },
  {
    "partNumber": 329,
    "partName": "PS KANAKPUR SOUTH"
  },
  {
    "partNumber": 330,
    "partName": "PS SILAUNI"
  },
  {
    "partNumber": 331,
    "partName": "CS SARAI SAGAR PRATHAM KACHHA"
  },
  {
    "partNumber": 332,
    "partName": "CS SARAI SAGAR DITAY KACHHA"
  },
  {
    "partNumber": 333,
    "partName": "PS RAMPUR MAYA"
  },
  {
    "partNumber": 334,
    "partName": "CS JAGDISHPUR TANDUALI"
  },
  {
    "partNumber": 335,
    "partName": "PS MOHAMMADPUR KASBA"
  },
  {
    "partNumber": 336,
    "partName": "PS DILASIGANJ UTTARI"
  },
  {
    "partNumber": 337,
    "partName": "PS DILASIGANJ DAKCHHRI"
  },
  {
    "partNumber": 338,
    "partName": "PS DILASIGANJ EXTRA ROOM"
  },
  {
    "partNumber": 339,
    "partName": "PS KAUDILLA"
  },
  {
    "partNumber": 340,
    "partName": "PS BAIHARI"
  },
  {
    "partNumber": 341,
    "partName": "PS ALHADIPUR"
  },
  {
    "partNumber": 342,
    "partName": "PS SONAURA"
  },
  {
    "partNumber": 343,
    "partName": "CS DEVRA DAUDPUR ROOM NO.-1"
  },
  {
    "partNumber": 344,
    "partName": "CS DEVRA DAUDPUR ROOM NO.-2"
  },
  {
    "partNumber": 345,
    "partName": "CS SAMANTHA NORTH"
  },
  {
    "partNumber": 346,
    "partName": "CS SAMANTHA SOUTH"
  },
  {
    "partNumber": 347,
    "partName": "PS TANDUALI NORTH"
  },
  {
    "partNumber": 348,
    "partName": "PS TANDUALI SOUTH"
  },
  {
    "partNumber": 349,
    "partName": "PS RAJPALIYA ROOM NO.- 1"
  },
  {
    "partNumber": 350,
    "partName": "PS RAJPALIYA ROOM NO.- 2"
  },
  {
    "partNumber": 351,
    "partName": "PS GANGAPUR GRANT ROOM NO- 1"
  },
  {
    "partNumber": 352,
    "partName": "PS GANGAPUR GRANT ROOM NO- 2"
  },
  {
    "partNumber": 353,
    "partName": "PS KAJIPUR GADAR ROOM NO- 1"
  },
  {
    "partNumber": 354,
    "partName": "PS KAJIPUR GADAR ROOM NO- 2"
  },
  {
    "partNumber": 355,
    "partName": "PS PAKRAILA PRATHAM KACHHA"
  },
  {
    "partNumber": 356,
    "partName": "PS PAKRAILA DITAY KACHHA"
  },
  {
    "partNumber": 357,
    "partName": "PS RAMNAGAR MISHRAULI"
  },
  {
    "partNumber": 358,
    "partName": "PS RASOOLPUR PRATHAM"
  },
  {
    "partNumber": 359,
    "partName": "PS RAJAPUR"
  },
  {
    "partNumber": 360,
    "partName": "SUBHASH INTER COLLEGE SARAIYA WEST"
  },
  {
    "partNumber": 361,
    "partName": "SUBHASH INTER COLLEGE SARAIYA EAST- 1"
  },
  {
    "partNumber": 362,
    "partName": "SUBHASH INTER COLLEGE SARAIYA EAST -2"
  },
  {
    "partNumber": 363,
    "partName": "SUBHASH INTER COLLEGE SARAIYA EXTRA ROOM"
  },
  {
    "partNumber": 364,
    "partName": "CS MANAPARA WEST"
  },
  {
    "partNumber": 365,
    "partName": "CS MANAPARA EAST"
  },
  {
    "partNumber": 366,
    "partName": "PS MAINPUR"
  },
  {
    "partNumber": 367,
    "partName": "UPS GOKULPUR FIRST ROOM"
  },
  {
    "partNumber": 368,
    "partName": "UPS GOKULPUR SECOND ROOM"
  },
  {
    "partNumber": 369,
    "partName": "PS PAUSARA UTTARI"
  },
  {
    "partNumber": 370,
    "partName": "PS PAUSARA DAKCHHRI"
  },
  {
    "partNumber": 371,
    "partName": "PS PAUSARA EXTRA ROOM"
  },
  {
    "partNumber": 372,
    "partName": "PS KADIPUR"
  },
  {
    "partNumber": 373,
    "partName": "PS HARDI"
  },
  {
    "partNumber": 374,
    "partName": "PS LALPUR EAST"
  },
  {
    "partNumber": 375,
    "partName": "PS LALPUR WEST"
  },
  {
    "partNumber": 376,
    "partName": "PS LALPUR EXTRA ROOM-1"
  },
  {
    "partNumber": 377,
    "partName": "PS LALPUR EXTRA ROOM"
  },
  {
    "partNumber": 378,
    "partName": "PS UNIYAR"
  },
  {
    "partNumber": 379,
    "partName": "PS MAHBOOBGANJ PRATHAM KACHHA"
  },
  {
    "partNumber": 380,
    "partName": "PS MAHBOOBGANJ DITAY KACHHA"
  },
  {
    "partNumber": 381,
    "partName": "PS SHERVAGHAT EAST"
  },
  {
    "partNumber": 382,
    "partName": "PS SHERVAGHAT WEST"
  },
  {
    "partNumber": 383,
    "partName": "PS ISHAPUR"
  },
  {
    "partNumber": 384,
    "partName": "PS DEVAPUR NORTH"
  },
  {
    "partNumber": 385,
    "partName": "PS DEVAPUR SOUTH"
  },
  {
    "partNumber": 386,
    "partName": "UPS RUHIYAWAN EAST"
  },
  {
    "partNumber": 387,
    "partName": "UPS RUHIYAWAN WEST"
  },
  {
    "partNumber": 388,
    "partName": "UPS RUHIYAWAN MADHYA"
  },
  {
    "partNumber": 389,
    "partName": "PS SARAIYA REVARI"
  },
  {
    "partNumber": 390,
    "partName": "PS BHITAURA NORTH"
  },
  {
    "partNumber": 391,
    "partName": "PS BHITAURA SOUTH"
  },
  {
    "partNumber": 392,
    "partName": "PS REVRI ROOM NO- 1"
  },
  {
    "partNumber": 393,
    "partName": "PS REVRI ROOM NO- 2"
  },
  {
    "partNumber": 394,
    "partName": "JANSEVA ASHRAM UMV BANDANPUR NORTH"
  },
  {
    "partNumber": 395,
    "partName": "JANSEVA ASHRAM UMV BANDANPUR SOUTH"
  },
  {
    "partNumber": 396,
    "partName": "PS GAUHANIYA NORTH"
  },
  {
    "partNumber": 397,
    "partName": "PS GAUHANIYA SOUTH"
  },
  {
    "partNumber": 398,
    "partName": "PS GAUHANIYA EXTRA ROOM"
  },
  {
    "partNumber": 399,
    "partName": "CS SAMADA EAST"
  },
  {
    "partNumber": 400,
    "partName": "CS SAMADA EXTRA ROOM"
  },
  {
    "partNumber": 401,
    "partName": "CS SAMADA WEST"
  },
  {
    "partNumber": 402,
    "partName": "A.N.D. INTER COLLEGE GOSHAIGANJ"
  },
  {
    "partNumber": 403,
    "partName": "GGIC GOSHAIGANJ WEST"
  },
  {
    "partNumber": 404,
    "partName": "GGIC GOSHAIGANJ EAST MIDDLE"
  },
  {
    "partNumber": 405,
    "partName": "GGIC GOSHAIGANJ EAST"
  },
  {
    "partNumber": 406,
    "partName": "GGIC GOSHAIGANJ EAST SECOND"
  },
  {
    "partNumber": 407,
    "partName": "GGIC GOSHAIGANJ SOUTHERN EAST"
  },
  {
    "partNumber": 408,
    "partName": "GGIC GOSHAIGANJ SOUTHERN NORTH"
  },
  {
    "partNumber": 409,
    "partName": "PS GOSHAIGANJ EAST"
  },
  {
    "partNumber": 410,
    "partName": "PS GOSHAIGANJ NORTH"
  },
  {
    "partNumber": 411,
    "partName": "PS GOSHAIGANJ SOUTHERN"
  },
  {
    "partNumber": 412,
    "partName": "RBN INTER COLLEGE GOSHAIGAN NORTHERN EAST"
  },
  {
    "partNumber": 413,
    "partName": "RBN INTER COLLEGE GOSHAIGAN EASTERN MIDDLE"
  },
  {
    "partNumber": 414,
    "partName": "RBN INTER COLLEGE GOSHAIGAN EAST MIDDLE -2"
  },
  {
    "partNumber": 415,
    "partName": "RBN INTER COLLEGE GOSHAIGAN EAST"
  },
  {
    "partNumber": 416,
    "partName": "RBN INTER COLLEGE GOSHAIGAN MIDDLE EAST 3"
  },
  {
    "partNumber": 417,
    "partName": "RBN INTER COLLEGE GOSHAIGAN SOUTHERN WEST"
  },
  {
    "partNumber": 418,
    "partName": "PS GADDOPUR HARDASPUR"
  },
  {
    "partNumber": 419,
    "partName": "PS CHIRKITHA"
  },
  {
    "partNumber": 420,
    "partName": "PS DHARUPUR"
  },
  {
    "partNumber": 421,
    "partName": "PS RAMAPUR PURVI"
  },
  {
    "partNumber": 422,
    "partName": "PS RAMAPUR PASHCHIMI"
  },
  {
    "partNumber": 423,
    "partName": "PS RAMAPUR"
  },
  {
    "partNumber": 424,
    "partName": "PS DEVGIRIYA"
  },
  {
    "partNumber": 425,
    "partName": "CS REHDI"
  },
  {
    "partNumber": 426,
    "partName": "PANCHAYAT BHAWAN AANAPUR SRAIYA"
  },
  {
    "partNumber": 427,
    "partName": "CS VEERSHAHPUR"
  },
  {
    "partNumber": 428,
    "partName": "CS KHIRAUNI"
  },
  {
    "partNumber": 429,
    "partName": "PS BERA"
  },
  {
    "partNumber": 430,
    "partName": "CS TRILOKPUR"
  },
  {
    "partNumber": 431,
    "partName": "PS BODHIPUR"
  },
  {
    "partNumber": 432,
    "partName": "JHS BODHIPUR PARMANPUR"
  },
  {
    "partNumber": 433,
    "partName": "CS JAITA"
  },
  {
    "partNumber": 434,
    "partName": "DEVKINANADAN RANGNARAIN JHS AMSIN EAST"
  },
  {
    "partNumber": 435,
    "partName": "DEVKINANADAN RANGNARAIN JHS AMSIN MIDDLE"
  },
  {
    "partNumber": 436,
    "partName": "DEVKINANADAN RANGNARAIN JHS AMSIN EXTRA ROOM"
  },
  {
    "partNumber": 437,
    "partName": "PS DAHLAWA AMSIN"
  }
]