[
  {
    "partNumber": 1,
    "partName": "AMICHAND INTER COLLEGE KASNA ROOM N0. 1"
  },
  {
    "partNumber": 2,
    "partName": "AMICHAND INTER COLLEGE KASNA ROOM N0. 2"
  },
  {
    "partNumber": 3,
    "partName": "AMICHAND INTER COLLEGE KASNA ROOM N0. 3"
  },
  {
    "partNumber": 4,
    "partName": "AMICHAND INTER COLLEGE KASNA ROOM N0. 4"
  },
  {
    "partNumber": 5,
    "partName": "AMICHAND INTER COLLEGE KASNA ROOM N0. 5"
  },
  {
    "partNumber": 6,
    "partName": "AMICHAND INTER COLLEGE KASNA ROOM N0. 6"
  },
  {
    "partNumber": 7,
    "partName": "KENDRIYA VIDHYALAY SECTOR P-3 ROOM N0. 1"
  },
  {
    "partNumber": 8,
    "partName": "KENDRIYA VIDHYALAY SECTOR P-3 ROOM N0. 2"
  },
  {
    "partNumber": 9,
    "partName": "KENDRIYA VIDHYALAY SECTOR P-3 ROOM N0. 3"
  },
  {
    "partNumber": 10,
    "partName": "KENDRIYA VIDHYALAY SECTOR P-3 ROOM N0. 4"
  },
  {
    "partNumber": 11,
    "partName": "URSULINE CONVENT SENIOR SECONDARY SCHOOL SEC-36 ROOM N0. 1"
  },
  {
    "partNumber": 12,
    "partName": "URSULINE CONVENT SENIOR SECONDARY SCHOOL SEC-36 ROOM N0. 2"
  },
  {
    "partNumber": 13,
    "partName": "URSULINE CONVENT SENIOR SECONDARY SCHOOL SEC-36 ROOM N0. 3"
  },
  {
    "partNumber": 14,
    "partName": "URSULINE CONVENT SENIOR SECONDARY SCHOOL SEC-36 ROOM N0. 4"
  },
  {
    "partNumber": 15,
    "partName": "URSULINE CONVENT SENIOR SECONDARY SCHOOL SEC-36 ROOM N0. 5"
  },
  {
    "partNumber": 16,
    "partName": "URSULINE CONVENT SENIOR SECONDARY SCHOOL SEC-36 ROOM N0. 6"
  },
  {
    "partNumber": 17,
    "partName": "URSULINE CONVENT SENIOR SECONDARY SCHOOL SEC-36 ROOM N0. 7"
  },
  {
    "partNumber": 18,
    "partName": "URSULINE CONVENT SENIOR SECONDARY SCHOOL SEC-36 ROOM N0. 8"
  },
  {
    "partNumber": 19,
    "partName": "COMMUNITY CENTER SIGMA 4 GREATER NOIDA ROOM NO 1"
  },
  {
    "partNumber": 20,
    "partName": "COMMUNITY CENTER SIGMA 4 GREATER NOIDA ROOM NO 2"
  },
  {
    "partNumber": 21,
    "partName": "PRIMARY SCHOOL BIRONDA ROOM NO 1"
  },
  {
    "partNumber": 22,
    "partName": "SAMSARA WORLD PUBLIC SCHOOL PI 1 GREATER NOIDA ROOM NO 1"
  },
  {
    "partNumber": 23,
    "partName": "SAMSARA WORLD PUBLIC SCHOOL PI 1 GREATER NOIDA ROOM NO 2"
  },
  {
    "partNumber": 24,
    "partName": "SAMSARA WORLD PUBLIC SCHOOL PI 1 GREATER NOIDA ROOM NO 3"
  },
  {
    "partNumber": 25,
    "partName": "SAMSARA WORLD PUBLIC SCHOOL PI 1 GREATER NOIDA ROOM NO 4"
  },
  {
    "partNumber": 26,
    "partName": "SAMSARA WORLD PUBLIC SCHOOL PI 1 GREATER NOIDA ROOM NO 5"
  },
  {
    "partNumber": 27,
    "partName": "PRIMARY SCHOOL DADHA ROOM NO 1"
  },
  {
    "partNumber": 28,
    "partName": "PRIMARY SCHOOL DADHA ROOM NO 2"
  },
  {
    "partNumber": 29,
    "partName": "PRIMARY SCHOOL SIRSA ROOM NO 1"
  },
  {
    "partNumber": 30,
    "partName": "PRIMARY SCHOOL SIRSA ROOM NO 2"
  },
  {
    "partNumber": 31,
    "partName": "PRIMARY SCHOOL KHANPUR ROOM NO 1"
  },
  {
    "partNumber": 32,
    "partName": "PRIMARY SCHOOL KHANPUR ROOM NO 2"
  },
  {
    "partNumber": 33,
    "partName": "PRIMARY SCHOOL LUKSAR ROOM NO. 1"
  },
  {
    "partNumber": 34,
    "partName": "PRIMARY SCHOOL MURSHADPUR ROOM NO 1"
  },
  {
    "partNumber": 35,
    "partName": "COMPOSITE SCHOOL GHARBRA ROOM NO 1"
  },
  {
    "partNumber": 36,
    "partName": "COMPOSITE SCHOOL GHARBRA ROOM NO 2"
  },
  {
    "partNumber": 37,
    "partName": "JUNIOR HIGH SCHOOL ATTAI MURADPUR ROOM NO 1"
  },
  {
    "partNumber": 38,
    "partName": "PRIMARY SCHOOL IMALIAKA ROOM NO 1"
  },
  {
    "partNumber": 39,
    "partName": "PRIMARY SCHOOL IMALIAKA ROOM NO 2"
  },
  {
    "partNumber": 40,
    "partName": "PRIMARY SCHOOL LADPURA ROOM NO 1"
  },
  {
    "partNumber": 41,
    "partName": "PRIMARY SCHOOL LADPURA ROOM NO 2"
  },
  {
    "partNumber": 42,
    "partName": "PRIMARY SCHOOL LADPURA ROOM NO 3"
  },
  {
    "partNumber": 43,
    "partName": "PRIMARY SCHOOL GHANGHOLA ROOM NO 1"
  },
  {
    "partNumber": 44,
    "partName": "PRIMARY SCHOOL GHANGHOLA ROOM NO 2"
  },
  {
    "partNumber": 45,
    "partName": "PRIMARY SCHOOL GHANGHOLA ROOM NO 3"
  },
  {
    "partNumber": 46,
    "partName": "PRIMARY SCHOOL CHEERSI ROOM NO 1"
  },
  {
    "partNumber": 47,
    "partName": "UCHCH PRIMARY SCHOOL FAJAYALPUR ROOM NO 1"
  },
  {
    "partNumber": 48,
    "partName": "UCHCH PRIMARY SCHOOL FAJAYALPUR ROOM NO 2"
  },
  {
    "partNumber": 49,
    "partName": "UCHCH PRIMARY SCHOOL DAULARAJPURA ROOM NO 1"
  },
  {
    "partNumber": 50,
    "partName": "UCHCH PRIMARY SCHOOL DAULARAJPURA ROOM NO 2"
  },
  {
    "partNumber": 51,
    "partName": "PRIMARY SCHOOL SALEHPUR ROOM NO 1"
  },
  {
    "partNumber": 52,
    "partName": "PRIMARY SCHOOL MANDPA ROOM NO 1"
  },
  {
    "partNumber": 53,
    "partName": "PRIMARY SCHOOL MANDPA ROOM NO 2"
  },
  {
    "partNumber": 54,
    "partName": "PRIMARY SCHOOL NO 2 JAMALPUR ROOM NO 1"
  },
  {
    "partNumber": 55,
    "partName": "PRIMARY SCHOOL NO 2 JAMALPUR ROOM NO 2"
  },
  {
    "partNumber": 56,
    "partName": "JUNIOR HIGH SCHOOL RAJPUR KALA ROOM NO 1"
  },
  {
    "partNumber": 57,
    "partName": "PRIMARY SCHOOL CHITI ROOM NO 1"
  },
  {
    "partNumber": 58,
    "partName": "PRIMARY SCHOOL CHITI ROOM NO 2"
  },
  {
    "partNumber": 59,
    "partName": "PRIMARY SCHOOL CHITI ROOM NO 3"
  },
  {
    "partNumber": 60,
    "partName": "PRIMARY SCHOOL NANGLA CHITI ROOM NO 1"
  },
  {
    "partNumber": 61,
    "partName": "PRIMARY SCHOOL DEVTA ROOM NO 1"
  },
  {
    "partNumber": 62,
    "partName": "PRIMARY SCHOOL DEVTA ROOM NO 2"
  },
  {
    "partNumber": 63,
    "partName": "PATEL INTER COLLEGE ASTAULI ROOM NO. 1"
  },
  {
    "partNumber": 64,
    "partName": "PATEL INTER COLLEGE ASTAULI ROOM NO. 2"
  },
  {
    "partNumber": 65,
    "partName": "PATEL INTER COLLEGE ASTAULI ROOM NO. 3"
  },
  {
    "partNumber": 66,
    "partName": "CHAUDHARY LAXMI NARAYAN INTER COLLEGE MANDI SHYAMNAGAR URF KHERLI HAFIZPUR ROOM NO. 1"
  },
  {
    "partNumber": 67,
    "partName": "CHAUDHARY LAXMI NARAYAN INTER COLLEGE MANDI SHYAMNAGAR URF KHERLI HAFIZPUR ROOM NO. 2"
  },
  {
    "partNumber": 68,
    "partName": "CHAUDHARY LAXMI NARAYAN INTER COLLEGE MANDI SHYAMNAGAR URF KHERLI HAFIZPUR ROOM NO. 3"
  },
  {
    "partNumber": 69,
    "partName": "CHAUDHARY LAXMI NARAYAN INTER COLLEGE MANDI SHYAMNAGAR URF KHERLI HAFIZPUR ROOM NO. 4"
  },
  {
    "partNumber": 70,
    "partName": "CHAUDHARY LAXMI NARAYAN INTER COLLEGE MANDI SHYAMNAGAR URF KHERLI HAFIZPUR ROOM NO. 5"
  },
  {
    "partNumber": 71,
    "partName": "CHAUDHARY LAXMI NARAYAN INTER COLLEGE MANDI SHYAMNAGAR URF KHERLI HAFIZPUR ROOM NO. 6"
  },
  {
    "partNumber": 72,
    "partName": "PRIMARY SCHOOL PANCHAYATAN INAYATPUR ROOM NO. 1"
  },
  {
    "partNumber": 73,
    "partName": "PRIMARY SCHOOL PANCHAYATAN INAYATPUR ROOM NO. 2"
  },
  {
    "partNumber": 74,
    "partName": "UCHCH PRIMARY SCHOOL GIRDHARPUR ROOM NO. 1"
  },
  {
    "partNumber": 75,
    "partName": "UCHCH PRIMARY SCHOOL GIRDHARPUR ROOM NO. 2"
  },
  {
    "partNumber": 76,
    "partName": "PRIMARY SCHOOL RAUNI ROOM NO 1"
  },
  {
    "partNumber": 77,
    "partName": "PRIMARY SCHOOL SALEMPUR GUJAR ROOM NO 1"
  },
  {
    "partNumber": 78,
    "partName": "PRIMARY SCHOOL SALEMPUR GUJAR ROOM NO 2"
  },
  {
    "partNumber": 79,
    "partName": "PRIMARY SCHOOL SALEMPUR GUJAR ROOM NO 3"
  },
  {
    "partNumber": 80,
    "partName": "PRIMARY SCHOOL AMINABAD URF NYANA ROOM NO 1"
  },
  {
    "partNumber": 81,
    "partName": "NEHA PUBLIC SCHOOL RAMPUR MAJRA ROOM NO 1"
  },
  {
    "partNumber": 82,
    "partName": "NEHA PUBLIC SCHOOL RAMPUR MAJRA ROOM NO 2"
  },
  {
    "partNumber": 83,
    "partName": "PRIMARY SCHOOL KULIPURA ROOM NO 1"
  },
  {
    "partNumber": 84,
    "partName": "RAJENDRA INTER COLLEGE BILASPUR ROOM NO 1"
  },
  {
    "partNumber": 85,
    "partName": "RAJENDRA INTER COLLEGE BILASPUR ROOM NO 2"
  },
  {
    "partNumber": 86,
    "partName": "RAJENDRA INTER COLLEGE BILASPUR ROOM NO 3"
  },
  {
    "partNumber": 87,
    "partName": "RAJENDRA INTER COLLEGE BILASPUR ROOM NO 4"
  },
  {
    "partNumber": 88,
    "partName": "RAJENDRA INTER COLLEGE BILASPUR ROOM NO 5"
  },
  {
    "partNumber": 89,
    "partName": "RAJENDRA INTER COLLEGE BILASPUR ROOM NO 6"
  },
  {
    "partNumber": 90,
    "partName": "RAJENDRA INTER COLLEGE BILASPUR ROOM NO 7"
  },
  {
    "partNumber": 91,
    "partName": "SHIVRAJ SHARMA INTER COLLEGE BILASPUR ROOM NO 1"
  },
  {
    "partNumber": 92,
    "partName": "SHIVRAJ SHARMA INTER COLLEGE BILASPUR ROOM NO 2"
  },
  {
    "partNumber": 93,
    "partName": "SHIVRAJ SHARMA INTER COLLEGE BILASPUR ROOM NO 3"
  },
  {
    "partNumber": 94,
    "partName": "SHIVRAJ SHARMA INTER COLLEGE BILASPUR ROOM NO 4"
  },
  {
    "partNumber": 95,
    "partName": "PRIMARY SCHOOL AZAMPUR GARHI ROOM NO 1"
  },
  {
    "partNumber": 96,
    "partName": "PRIMARY SCHOOL BANZARPUR ROOM NO 1"
  },
  {
    "partNumber": 97,
    "partName": "PRIMARY SCHOOL BANZARPUR ROOM NO 2"
  },
  {
    "partNumber": 98,
    "partName": "PRIMARY SCHOOL SARAKPUR ROOM NO 1"
  },
  {
    "partNumber": 99,
    "partName": "PRIMARY SCHOOL BHATTA ROOM NO. 1"
  },
  {
    "partNumber": 100,
    "partName": "PRIMARY SCHOOL BHATTA ROOM NO. 2"
  },
  {
    "partNumber": 101,
    "partName": "PRIMARY SCHOOL BHATTA ROOM NO. 3"
  },
  {
    "partNumber": 102,
    "partName": "PRIMARY SCHOOL CHUHADPUR BANGAR ROOM NO 1"
  },
  {
    "partNumber": 103,
    "partName": "PRIMARY PATHSHALA TALDA ROOM NO 1"
  },
  {
    "partNumber": 104,
    "partName": "PRIMARY PATHSHALA TALDA ROOM NO 2"
  },
  {
    "partNumber": 105,
    "partName": "PRIMARY SCHOOL HATEWA ROOM NO. 1"
  },
  {
    "partNumber": 106,
    "partName": "PRIMARY SCHOOL DALELGARH ROOM NO 1"
  },
  {
    "partNumber": 107,
    "partName": "PRIMARY SCHOOL DALELGARH ROOM NO 2"
  },
  {
    "partNumber": 108,
    "partName": "PRIMARY SCHOOL BAGPUR ROOM NO 1"
  },
  {
    "partNumber": 109,
    "partName": "PRIMARY SCHOOL PEEPALKA SURATPUR ROOM NO 1"
  },
  {
    "partNumber": 110,
    "partName": "PRIMARY SCHOOL PEEPALKA SURATPUR ROOM NO 2"
  },
  {
    "partNumber": 111,
    "partName": "PRIMARY SCHOOL BISICH ROOM NO. 1"
  },
  {
    "partNumber": 112,
    "partName": "PRIMARY SCHOOL DADUPUR DANKOUR ROOM NO 1"
  },
  {
    "partNumber": 113,
    "partName": "PRIMARY SCHOOL DADUPUR DANKOUR ROOM NO 2"
  },
  {
    "partNumber": 114,
    "partName": "PRIMARY SCHOOL DADUPUR DANKOUR ROOM NO 3"
  },
  {
    "partNumber": 115,
    "partName": "PRIMARY SCHOOL AMARPUR ROOM NO 1"
  },
  {
    "partNumber": 116,
    "partName": "PRIMARY SCHOOL NANUA KA RAJPUR ROOM NO 1"
  },
  {
    "partNumber": 117,
    "partName": "UCHCH PRIMARY SCHOOL NAWADA ROOM NO 1"
  },
  {
    "partNumber": 118,
    "partName": "UCHCH PRIMARY SCHOOL NAWADA ROOM NO 2"
  },
  {
    "partNumber": 119,
    "partName": "UCHCH PRIMARY SCHOOL NAWADA ROOM NO 3"
  },
  {
    "partNumber": 120,
    "partName": "PRIMARY SCHOOL KANARSA MAJRA KANARSI ROOM NO 1"
  },
  {
    "partNumber": 121,
    "partName": "PRIMARY SCHOOL KANARASI ROOM NO 1"
  },
  {
    "partNumber": 122,
    "partName": "PRIMARY SCHOOL KANARASI ROOM NO 2"
  },
  {
    "partNumber": 123,
    "partName": "PRIMARY SCHOOL JUNAIDPUR ROOM NO 1"
  },
  {
    "partNumber": 124,
    "partName": "PRIMARY SCHOOL JUNAIDPUR ROOM NO 2"
  },
  {
    "partNumber": 125,
    "partName": "PRIMARY SCHOOL CHACHULA ROOM NO 1"
  },
  {
    "partNumber": 126,
    "partName": "PRIMARY SCHOOL CHACHULA ROOM NO 2"
  },
  {
    "partNumber": 127,
    "partName": "PRIMARY SCHOOL ROSHANPUR ROOM NO 1"
  },
  {
    "partNumber": 128,
    "partName": "PRIMARY SCHOOL DHANAURI ROOM NO 1"
  },
  {
    "partNumber": 129,
    "partName": "PRIMARY SCHOOL DHANAURI ROOM NO 2"
  },
  {
    "partNumber": 130,
    "partName": "SUNHARI LAL BALMUKUND INTER COLLEGE DHANAURI ROOM NO. 1"
  },
  {
    "partNumber": 131,
    "partName": "SUNHARI LAL BALMUKUND INTER COLLEGE DHANAURI ROOM NO. 2"
  },
  {
    "partNumber": 132,
    "partName": "PRIMARY SCHOOL THASRANA ROOM NO 1"
  },
  {
    "partNumber": 133,
    "partName": "PRIMARY SCHOOL CHANGULI ROOM NO 1"
  },
  {
    "partNumber": 134,
    "partName": "PRIMARY SCHOOL USMANPUR ROOM NO 1"
  },
  {
    "partNumber": 135,
    "partName": "PRIMARY SCHOOL USMANPUR ROOM NO 2"
  },
  {
    "partNumber": 136,
    "partName": "PRIMARY SCHOOL MUTAINA ROOM NO 1"
  },
  {
    "partNumber": 137,
    "partName": "KISAN INTER COLLEGE PARSAUL ROOM NO 1"
  },
  {
    "partNumber": 138,
    "partName": "KISAN INTER COLLEGE PARSAUL ROOM NO 2"
  },
  {
    "partNumber": 139,
    "partName": "KISAN INTER COLLEGE PARSAUL ROOM NO 3"
  },
  {
    "partNumber": 140,
    "partName": "PRIMARY SCHOOL AACHEPUR ROOM NO 1"
  },
  {
    "partNumber": 141,
    "partName": "PRIMARY SCHOOL AACHEPUR ROOM NO 2"
  },
  {
    "partNumber": 142,
    "partName": "PRIMARY SCHOOL CHANDPUR ROOM NO 1"
  },
  {
    "partNumber": 143,
    "partName": "PRIMARY SCHOOL NILAUNI ROOM NO. 1"
  },
  {
    "partNumber": 144,
    "partName": "PRIMARY SCHOOL NILAUNI ROOM NO. 2"
  },
  {
    "partNumber": 145,
    "partName": "PRIMARY SCHOOL SHAHPUR ROOM NO 1"
  },
  {
    "partNumber": 146,
    "partName": "PRIMARY SCHOOL MIRZAPUR ROOM NO 1"
  },
  {
    "partNumber": 147,
    "partName": "PRIMARY SCHOOL MIRZAPUR ROOM NO 2"
  },
  {
    "partNumber": 148,
    "partName": "SHRI HARDWARI LAL JANHIT HIGHER SECONDARY SCHOOL MIRZAPUR ROOM NO. 1"
  },
  {
    "partNumber": 149,
    "partName": "SHRI HARDWARI LAL JANHIT HIGHER SECONDARY SCHOOL MIRZAPUR ROOM NO. 2"
  },
  {
    "partNumber": 150,
    "partName": "SHRI HARDWARI LAL JANHIT HIGHER SECONDARY SCHOOL MIRZAPUR ROOM NO. 3"
  },
  {
    "partNumber": 151,
    "partName": "PRIMARY SCHOOL CHAPARGARH ROOM NO 1"
  },
  {
    "partNumber": 152,
    "partName": "PRIMARY SCHOOL RAMPUR BANGAR ROOM NO 1"
  },
  {
    "partNumber": 153,
    "partName": "PRIMARY SCHOOL ACHHEJA BUJURG ROOM NO. 1"
  },
  {
    "partNumber": 154,
    "partName": "PRIMARY SCHOOL ACHHEJA BUJURG ROOM NO. 2"
  },
  {
    "partNumber": 155,
    "partName": "PRIMARY SCHOOL DUNGARPUR RILKA ROOM NO 1"
  },
  {
    "partNumber": 156,
    "partName": "PRIMARY SCHOOL DUNGARPUR RILKA ROOM NO 2"
  },
  {
    "partNumber": 157,
    "partName": "PRIMARY SCHOOL MOHAMMADPUR GUJAR ROOM NO.1"
  },
  {
    "partNumber": 158,
    "partName": "BIHARI LAL INTER COLLEGE DANKAUR ROOM NO. 1"
  },
  {
    "partNumber": 159,
    "partName": "BIHARI LAL INTER COLLEGE DANKAUR ROOM NO. 2"
  },
  {
    "partNumber": 160,
    "partName": "BIHARI LAL INTER COLLEGE DANKAUR ROOM NO. 3"
  },
  {
    "partNumber": 161,
    "partName": "BIHARI LAL INTER COLLEGE DANKAUR ROOM NO. 4"
  },
  {
    "partNumber": 162,
    "partName": "BIHARI LAL INTER COLLEGE DANKAUR ROOM NO. 5"
  },
  {
    "partNumber": 163,
    "partName": "BIHARI LAL INTER COLLEGE DANKAUR ROOM NO. 6"
  },
  {
    "partNumber": 164,
    "partName": "BIHARI LAL INTER COLLEGE DANKAUR ROOM NO. 7"
  },
  {
    "partNumber": 165,
    "partName": "BIHARI LAL INTER COLLEGE DANKAUR ROOM NO. 8"
  },
  {
    "partNumber": 166,
    "partName": "PRE SECONDARY SCHOOL TOWN AREA DANKAUR ROOM NO 1"
  },
  {
    "partNumber": 167,
    "partName": "PRE SECONDARY SCHOOL TOWN AREA DANKAUR ROOM NO 2"
  },
  {
    "partNumber": 168,
    "partName": "PRE SECONDARY SCHOOL TOWN AREA DANKAUR ROOM NO 3"
  },
  {
    "partNumber": 169,
    "partName": "PRE SECONDARY SCHOOL TOWN AREA DANKAUR ROOM NO 4"
  },
  {
    "partNumber": 170,
    "partName": "PRIMARY SCHOOL NO 1 TOWN AREA DANKAUR ROOM NO 1"
  },
  {
    "partNumber": 171,
    "partName": "PRIMARY SCHOOL NO 1 TOWN AREA DANKAUR ROOM NO 2"
  },
  {
    "partNumber": 172,
    "partName": "UCHCH PRATHMIK VIDYALYA DEREEN GUJRAN ROOM N0. 1"
  },
  {
    "partNumber": 173,
    "partName": "UCHCH PRATHMIK VIDYALYA DEREEN GUJRAN ROOM N0. 2"
  },
  {
    "partNumber": 174,
    "partName": "KISAN ADRASH INTER COLLEGE DANKAUR ROOM NO. 1"
  },
  {
    "partNumber": 175,
    "partName": "PRIMARY SCHOOL ATTA GUJRAAN ROOM NO. 1"
  },
  {
    "partNumber": 176,
    "partName": "PRIMARY SCHOOL ATTA GUJRAAN ROOM NO. 2"
  },
  {
    "partNumber": 177,
    "partName": "PRIMARY SCHOOL ATTA GUJRAAN ROOM NO. 3"
  },
  {
    "partNumber": 178,
    "partName": "PRIMARY SCHOOL JAGANPUR AFZALPUR ROOM NO 1"
  },
  {
    "partNumber": 179,
    "partName": "PRIMARY SCHOOL AURANGPUR ROOM NO 1"
  },
  {
    "partNumber": 180,
    "partName": "PRIMARY SCHOOL FATEHPUR ATTA ROOM NO. 1"
  },
  {
    "partNumber": 181,
    "partName": "PRIMARY SCHOOL FATEHPUR ATTA ROOM NO. 2"
  },
  {
    "partNumber": 182,
    "partName": "PRIMARY SCHOOL SALARPUR ROOM NO 1"
  },
  {
    "partNumber": 183,
    "partName": "PRIMARY SCHOOL SALARPUR ROOM NO 2"
  },
  {
    "partNumber": 184,
    "partName": "PRIMARY SCHOOL MOOJKHEDA ROOM NO. 1"
  },
  {
    "partNumber": 185,
    "partName": "PRIMARY SCHOOL BALLUKHERA MAJRA MOONJKHERA ROOM NO. 1"
  },
  {
    "partNumber": 186,
    "partName": "PRIMARY SCHOOL DERIN KHUBAN MAJRA MOONJKHERA ROOM NO 1"
  },
  {
    "partNumber": 187,
    "partName": "PRIMARY SCHOOL KHERLI BHAV ROOM NO 1"
  },
  {
    "partNumber": 188,
    "partName": "PRIMARY SCHOOL KHERLI BHAV ROOM NO 2"
  },
  {
    "partNumber": 189,
    "partName": "PRIMARY SCHOOL LATIFPUR ROOM NO 1"
  },
  {
    "partNumber": 190,
    "partName": "PRIMARY SCHOOL KADALPUR ROOM NO 1"
  },
  {
    "partNumber": 191,
    "partName": "PRIMARY SCHOOL KADALPUR ROOM NO 2"
  },
  {
    "partNumber": 192,
    "partName": "PRIMARY SCHOOL MAKANPUR BANGAR ROOM NO 1"
  },
  {
    "partNumber": 193,
    "partName": "PRIMARY SCHOOL MAKANPUR KHADAR ROOM NO 1"
  },
  {
    "partNumber": 194,
    "partName": "PRIMARY SCHOOL RAMPUR KHADAR ROOM NO 1"
  },
  {
    "partNumber": 195,
    "partName": "JUNIOR HIGH SCHOOL MOHAMMADABAD KHEDA ROOM NO 1"
  },
  {
    "partNumber": 196,
    "partName": "JUNIOR HIGH SCHOOL MOHAMMADABAD KHEDA ROOM NO 2"
  },
  {
    "partNumber": 197,
    "partName": "PRIMARY SCHOOL TAKIPUR BANGAR ROOM NO 1"
  },
  {
    "partNumber": 198,
    "partName": "PRIMARY SCHOOL ANWARGARH BANGAR ROOM NO 1"
  },
  {
    "partNumber": 199,
    "partName": "JUNIOR HIGH SCHOOL RAUNIJA ROOM NO 1"
  },
  {
    "partNumber": 200,
    "partName": "JUNIOR HIGH SCHOOL RAUNIJA ROOM NO 2"
  },
  {
    "partNumber": 201,
    "partName": "JUNIOR HIGH SCHOOL RAUNIJA ROOM NO 3"
  },
  {
    "partNumber": 202,
    "partName": "PRIMARY SCHOOL RUSTAMPUR ROOM NO 1"
  },
  {
    "partNumber": 203,
    "partName": "PRIMARY SCHOOL CHAK JALALABAD ROOM NO 1"
  },
  {
    "partNumber": 204,
    "partName": "PRIMER SCHOOL NAGLA PADAM SINGH ROOM NO 1"
  },
  {
    "partNumber": 205,
    "partName": "PRIMARY SCHOOL NAGLA SHRIGOPAL ROOM NO 1"
  },
  {
    "partNumber": 206,
    "partName": "PRIMARY SCHOOL PACHOKARA ROOM NO 1"
  },
  {
    "partNumber": 207,
    "partName": "PRIMARY SCHOOL UTRAVALI ROOM NO 1"
  },
  {
    "partNumber": 208,
    "partName": "PRIMARY SCHOOL RASULPUR IQBAIL ROOM NO 1"
  },
  {
    "partNumber": 209,
    "partName": "UCHCH PRIMARY SCHOOL MOHAMMADPUR JADAUN ROOM NO 1"
  },
  {
    "partNumber": 210,
    "partName": "UCHCH PRIMARY SCHOOL MOHAMMADPUR JADAUN ROOM NO 2"
  },
  {
    "partNumber": 211,
    "partName": "PRIMARY SCHOOL DUGLI ROOM NO 1"
  },
  {
    "partNumber": 212,
    "partName": "PRIMARY SCHOOL HAJIPUR ROOM NO 1"
  },
  {
    "partNumber": 213,
    "partName": "INTER COLLEGE TOWN AREA RABUPURA ROOM NO 1"
  },
  {
    "partNumber": 214,
    "partName": "INTER COLLEGE TOWN AREA RABUPURA ROOM NO 2"
  },
  {
    "partNumber": 215,
    "partName": "INTER COLLEGE TOWN AREA RABUPURA ROOM NO 3"
  },
  {
    "partNumber": 216,
    "partName": "INTER COLLEGE TOWN AREA RABUPURA ROOM NO 4"
  },
  {
    "partNumber": 217,
    "partName": "INTER COLLEGE TOWN AREA RABUPURA ROOM NO 5"
  },
  {
    "partNumber": 218,
    "partName": "INTER COLLEGE TOWN AREA RABUPURA ROOM NO 6"
  },
  {
    "partNumber": 219,
    "partName": "INTER COLLEGE TOWN AREA RABUPURA ROOM NO 7"
  },
  {
    "partNumber": 220,
    "partName": "INTER COLLEGE TOWN AREA RABUPURA ROOM NO 8"
  },
  {
    "partNumber": 221,
    "partName": "INTER COLLEGE TOWN AREA RABUPURA ROOM NO 9"
  },
  {
    "partNumber": 222,
    "partName": "INTER COLLEGE TOWN AREA RABUPURA ROOM NO 10"
  },
  {
    "partNumber": 223,
    "partName": "SARASWATI SHISHU MANDIR INTER COLLEGE RABUPURA ROOM NO. 1"
  },
  {
    "partNumber": 224,
    "partName": "SARASWATI SHISHU MANDIR INTER COLLEGE RABUPURA ROOM NO. 2"
  },
  {
    "partNumber": 225,
    "partName": "PRIMARY SCHOOL TOWN AREA RABUPURA ROOM NO 1"
  },
  {
    "partNumber": 226,
    "partName": "PRIMARY SCHOOL TOWN AREA RABUPURA ROOM NO 2"
  },
  {
    "partNumber": 227,
    "partName": "PRIMARY SCHOOL TOWN AREA RABUPURA ROOM NO 3"
  },
  {
    "partNumber": 228,
    "partName": "JUNIOR HIGH SCHOOL BHAIPUR BRAHMANAN ROOM NO 1"
  },
  {
    "partNumber": 229,
    "partName": "JUNIOR HIGH SCHOOL BHAIPUR BRAHMANAN ROOM NO 2"
  },
  {
    "partNumber": 230,
    "partName": "PRIMARY SCHOOL MEHDIPUR BANGAR ROOM NO 1"
  },
  {
    "partNumber": 231,
    "partName": "PRIMARY SCHOOL MEHDIPUR BANGAR ROOM NO 2"
  },
  {
    "partNumber": 232,
    "partName": "PRIMARY SCHOOL MEHDIPUR BANGAR ROOM NO 3"
  },
  {
    "partNumber": 233,
    "partName": "PRIMARY SCHOOL SIRAULI BANGAR ROOM NO 1"
  },
  {
    "partNumber": 234,
    "partName": "PRIMARY SCHOOL SIRAULI BANGAR ROOM NO 2"
  },
  {
    "partNumber": 235,
    "partName": "PRIMARY SCHOOL DHANPURA ROOM NO 1"
  },
  {
    "partNumber": 236,
    "partName": "PRIMARY SCHOOL TIRTHALI ROOM NO 1"
  },
  {
    "partNumber": 237,
    "partName": "PRIMARY SCHOOL TIRTHALI ROOM NO 2"
  },
  {
    "partNumber": 238,
    "partName": "JUNIOR HIGH SCHOOL TIRTHALI ROOM NO 1"
  },
  {
    "partNumber": 239,
    "partName": "JUNIOR HIGH SCHOOL TIRTHALI ROOM NO 2"
  },
  {
    "partNumber": 240,
    "partName": "PRIMARY SCHOOL BHUNNATAGA ROOM NO 1"
  },
  {
    "partNumber": 241,
    "partName": "PRIMARY SCHOOL BHUNNATAGA ROOM NO 2"
  },
  {
    "partNumber": 242,
    "partName": "PRIMARY SCHOOL MAQSOODPUR ROOM NO 1"
  },
  {
    "partNumber": 243,
    "partName": "PRIMARY SCHOOL MAYANA ROOM NO 1"
  },
  {
    "partNumber": 244,
    "partName": "PRIMARY SCHOOL KALUPURA ROOM NO 1"
  },
  {
    "partNumber": 245,
    "partName": "PRIMARY SCHOOL KALUPURA ROOM NO 2"
  },
  {
    "partNumber": 246,
    "partName": "PRIMARY SCHOOL JAUNCHANA ROOM NO. 1"
  },
  {
    "partNumber": 247,
    "partName": "PRIMARY SCHOOL CHACHURA ROOM NO. 1"
  },
  {
    "partNumber": 248,
    "partName": "PRIMARY SCHOOL AMANULLAPUR URF MARHARA ROOM NO 1"
  },
  {
    "partNumber": 249,
    "partName": "PRIMARY SCHOOL AMANULLAPUR URF MARHARA ROOM NO 2"
  },
  {
    "partNumber": 250,
    "partName": "PRIMARY SCHOOL BHIKANPUR ROOM NO 1"
  },
  {
    "partNumber": 251,
    "partName": "PRIMARY SCHOOL AKALPUR ROOM NO 1"
  },
  {
    "partNumber": 252,
    "partName": "PRIMARY SCHOOL AKALPUR ROOM NO 2"
  },
  {
    "partNumber": 253,
    "partName": "PRIMARY SCHOOL MUDRAH ROOM NO 1"
  },
  {
    "partNumber": 254,
    "partName": "PRIMARY SCHOOL MUDRAH ROOM NO 2"
  },
  {
    "partNumber": 255,
    "partName": "PRIMARY SCHOOL ISMAILNAGAR URF BHOYRA ROOM NO 1"
  },
  {
    "partNumber": 256,
    "partName": "PRIMARY SCHOOL KANPUR ROOM NO 1"
  },
  {
    "partNumber": 257,
    "partName": "PRIMARY SCHOOL KANPUR ROOM NO 2"
  },
  {
    "partNumber": 258,
    "partName": "PRIMARY SCHOOL NAGLA SHAHPUR ROOM NO 1"
  },
  {
    "partNumber": 259,
    "partName": "PRIMARY SCHOOL BIRAMPUR ROOM NO 1"
  },
  {
    "partNumber": 260,
    "partName": "PRIMARY SCHOOL BIRAMPUR ROOM NO 2"
  },
  {
    "partNumber": 261,
    "partName": "PRIMARY SCHOOL CHAKBIRAMPUR ROOM NO 1"
  },
  {
    "partNumber": 262,
    "partName": "PRIMARY SCHOOL MURADGARHI ROOM NO 1"
  },
  {
    "partNumber": 263,
    "partName": "PRIMARY SCHOOL NAGLA BHATOUNA MAJRA KAROI BANGAR ROOM NO 1"
  },
  {
    "partNumber": 264,
    "partName": "PRIMARY SCHOOL NAGLA HUKAM SINGH MAJRA KAROLI ROOM NO 1"
  },
  {
    "partNumber": 265,
    "partName": "PRIMARY SCHOOL NAGLA HUKAM SINGH MAJRA KAROLI ROOM NO 2"
  },
  {
    "partNumber": 266,
    "partName": "PRIMARY SCHOOL NAGLA KANCHAN MAJRA KAROLI BANGAR ROOM NO 1"
  },
  {
    "partNumber": 267,
    "partName": "PRIMARY SCHOOL NAGLA CHANDAN MAJRA KAROLI ROOM NO 1"
  },
  {
    "partNumber": 268,
    "partName": "JUNIOR HIGH SCHOOL FALAIDA BANGAR ROOM NO 1"
  },
  {
    "partNumber": 269,
    "partName": "JUNIOR HIGH SCHOOL FALAIDA BANGAR ROOM NO 2"
  },
  {
    "partNumber": 270,
    "partName": "JUNIOR HIGH SCHOOL FALAIDA BANGAR ROOM NO 3"
  },
  {
    "partNumber": 271,
    "partName": "JUNIOR HIGH SCHOOL FALAIDA BANGAR ROOM NO 4"
  },
  {
    "partNumber": 272,
    "partName": "JUNIOR HIGH SCHOOL FALAIDA BANGAR ROOM NO 5"
  },
  {
    "partNumber": 273,
    "partName": "PRIMARY SCHOOL NAGLA HANDA MAJRA KURAIB ROOM NO 1"
  },
  {
    "partNumber": 274,
    "partName": "PRIMARY SCHOOL KUREB ROOM NO 1"
  },
  {
    "partNumber": 275,
    "partName": "JUNIOR HIGH SCHOOL KUREB ROOM NO 1"
  },
  {
    "partNumber": 276,
    "partName": "JUNIOR HIGH SCHOOL KUREB ROOM NO 2"
  },
  {
    "partNumber": 277,
    "partName": "JUNIOR HIGH SCHOOL KUREB ROOM NO 3"
  },
  {
    "partNumber": 278,
    "partName": "PRIMARY SCHOOL RANHERA ROOM NO 1"
  },
  {
    "partNumber": 279,
    "partName": "PRIMARY SCHOOL RANHERA ROOM NO 2"
  },
  {
    "partNumber": 280,
    "partName": "PRIMARY SCHOOL RANHERA ROOM NO 3"
  },
  {
    "partNumber": 281,
    "partName": "PRIMARY SCHOOL RANHERA ROOM NO 4"
  },
  {
    "partNumber": 282,
    "partName": "PRIMARY SCHOOL DAYANATPUR ROOM NO 1"
  },
  {
    "partNumber": 283,
    "partName": "PRIMARY SCHOOL DAYANATPUR ROOM NO 2"
  },
  {
    "partNumber": 284,
    "partName": "INTER COLLEGE DAYANATPUR ROOM NO. 1"
  },
  {
    "partNumber": 285,
    "partName": "INTER COLLEGE DAYANATPUR ROOM NO. 2"
  },
  {
    "partNumber": 286,
    "partName": "INTER COLLEGE DAYANATPUR ROOM NO. 3"
  },
  {
    "partNumber": 287,
    "partName": "PRIMARY SCHOOL BEGUMABAD MAJRA DAYANATPUR ROOM NO 1"
  },
  {
    "partNumber": 288,
    "partName": "PRIMARY SCHOOL RAMPUR BANGAR ROOM NO 1"
  },
  {
    "partNumber": 289,
    "partName": "PRIMARY SCHOOL RAMPUR BANGAR ROOM NO 2"
  },
  {
    "partNumber": 290,
    "partName": "PRIMARY SCHOOL BALLABHNAGAR URF KARROL BANGAR ROOM NO 1"
  },
  {
    "partNumber": 291,
    "partName": "PRIMARY SCHOOL SIRSA MACHIPUR ROOM NO 1"
  },
  {
    "partNumber": 292,
    "partName": "PRIMARY SCHOOL SIRSA MACHIPUR ROOM NO 2"
  },
  {
    "partNumber": 293,
    "partName": "PRIMARY SCHOOL KISHOREPUR ROOM NO 1"
  },
  {
    "partNumber": 294,
    "partName": "PRIMARY SCHOOL KISHOREPUR ROOM NO 2"
  },
  {
    "partNumber": 295,
    "partName": "PRIMARY SCHOOL SABOTA MUSTAFABAD ROOM NO 1"
  },
  {
    "partNumber": 296,
    "partName": "PRIMARY SCHOOL SABOTA MUSTAFABAD ROOM NO 2"
  },
  {
    "partNumber": 297,
    "partName": "PRIMARY SCHOOL SABOTA MUSTAFABAD ROOM NO 3"
  },
  {
    "partNumber": 298,
    "partName": "PRIMARY SCHOOL MUKIMPUR SHIVARA ROOM NO 1"
  },
  {
    "partNumber": 299,
    "partName": "PRIMARY SCHOOL ALAUDDIN NAGAR URF DUDHERA ROOM NO 1"
  },
  {
    "partNumber": 300,
    "partName": "PRIMARY SCHOOL ALAUDDIN NAGAR URF DUDHERA ROOM NO 2"
  },
  {
    "partNumber": 301,
    "partName": "PRIMARY SCHOOL PAROHI ROOM NO 1"
  },
  {
    "partNumber": 302,
    "partName": "PRIMARY SCHOOL BANWARIWAS NO. NO. 1"
  },
  {
    "partNumber": 303,
    "partName": "PRIMARY SCHOOL BANWARIWAS NO. NO. 2"
  },
  {
    "partNumber": 304,
    "partName": "PRIMARY SCHOOL RAMNER ROOM NO 1"
  },
  {
    "partNumber": 305,
    "partName": "PRIMARY SCHOOL RAMNER ROOM NO 2"
  },
  {
    "partNumber": 306,
    "partName": "PRIMARY SCHOOL DHANASIYA ROOM NO 1"
  },
  {
    "partNumber": 307,
    "partName": "PRIMARY SCHOOL DASTAMPUR ROOM NO 1"
  },
  {
    "partNumber": 308,
    "partName": "PRIMARY SCHOOL DASTAMPUR ROOM NO 2"
  },
  {
    "partNumber": 309,
    "partName": "PRIMARY SCHOOL MOHABLIPUR ROOM NO 1"
  },
  {
    "partNumber": 310,
    "partName": "PRIMARY SCHOOL MILK KARIMABAD ROOM NO 1"
  },
  {
    "partNumber": 311,
    "partName": "PRIMARY SCHOOL ALIAHMADPUR URF GARHI ROOM NO 1"
  },
  {
    "partNumber": 312,
    "partName": "PRIMARY SCHOOL NO 01 THORA ROOM NO 1"
  },
  {
    "partNumber": 313,
    "partName": "PRIMARY SCHOOL NO 01 THORA ROOM NO 2"
  },
  {
    "partNumber": 314,
    "partName": "PRIMARY SCHOOL NO 01 THORA ROOM NO 3"
  },
  {
    "partNumber": 315,
    "partName": "PRIMARY SCHOOL NO 02 THORA ROOM NO 1"
  },
  {
    "partNumber": 316,
    "partName": "PRIMARY SCHOOL NO 02 THORA ROOM NO 2"
  },
  {
    "partNumber": 317,
    "partName": "DR BHIMRAO AMBEDKAR COMMUNITY CENTER BANKAPUR ROOM NO 1"
  },
  {
    "partNumber": 318,
    "partName": "DR BHIMRAO AMBEDKAR COMMUNITY CENTER BANKAPUR ROOM NO 2"
  },
  {
    "partNumber": 319,
    "partName": "PRIMARY SCHOOL NEEMKA SHAHJAHANPUR ROOM NO 1"
  },
  {
    "partNumber": 320,
    "partName": "PRIMARY SCHOOL NEEMKA SHAHJAHANPUR ROOM NO 2"
  },
  {
    "partNumber": 321,
    "partName": "JUNIOR HIGH SCHOOL NEEMKA SHAHJAHANPUR ROOM NO 1"
  },
  {
    "partNumber": 322,
    "partName": "PRIMARY SCHOOL SADULLAPUR URF MADALPUR ROOM NO. 1"
  },
  {
    "partNumber": 323,
    "partName": "PRIMARY SCHOOL KHWAJPUR ROOM NO 1"
  },
  {
    "partNumber": 324,
    "partName": "PRIMARY SCHOOL KHWAJPUR ROOM NO 2"
  },
  {
    "partNumber": 325,
    "partName": "PRIMARY SCHOOL JEWAR KHADAR ROOM NO. 1"
  },
  {
    "partNumber": 326,
    "partName": "SARASWATI SHISHU MANDIR TOWN AREA JEWAR ROOM NO 1"
  },
  {
    "partNumber": 327,
    "partName": "SARASWATI SHISHU MANDIR TOWN AREA JEWAR ROOM NO 2"
  },
  {
    "partNumber": 328,
    "partName": "SARASWATI SHISHU MANDIR TOWN AREA JEWAR ROOM NO 3"
  },
  {
    "partNumber": 329,
    "partName": "SARASWATI SHISHU MANDIR TOWN AREA JEWAR ROOM NO 4"
  },
  {
    "partNumber": 330,
    "partName": "SARASWATI SHISHU MANDIR TOWN AREA JEWAR ROOM NO 5"
  },
  {
    "partNumber": 331,
    "partName": "SARASWATI SHISHU MANDIR TOWN AREA JEWAR ROOM NO 6"
  },
  {
    "partNumber": 332,
    "partName": "SARASWATI SHISHU MANDIR TOWN AREA JEWAR ROOM NO 7"
  },
  {
    "partNumber": 333,
    "partName": "PRIMARY SCHOOL JAFRABAD ROOM NO 1"
  },
  {
    "partNumber": 334,
    "partName": "PRIMARY SCHOOL SAHABNAGAR ROOM NO 1"
  },
  {
    "partNumber": 335,
    "partName": "ADARSH ​​KANYA INTER COLLEGE TOWN AREA JEWAR ROOM NO 1"
  },
  {
    "partNumber": 336,
    "partName": "ADARSH ​​KANYA INTER COLLEGE TOWN AREA JEWAR ROOM NO 2"
  },
  {
    "partNumber": 337,
    "partName": "ADARSH ​​KANYA INTER COLLEGE TOWN AREA JEWAR ROOM NO 3"
  },
  {
    "partNumber": 338,
    "partName": "ADARSH ​​KANYA INTER COLLEGE TOWN AREA JEWAR ROOM NO 4"
  },
  {
    "partNumber": 339,
    "partName": "ADARSH ​​KANYA INTER COLLEGE TOWN AREA JEWAR ROOM NO 5"
  },
  {
    "partNumber": 340,
    "partName": "ADARSH ​​KANYA INTER COLLEGE TOWN AREA JEWAR ROOM NO 6"
  },
  {
    "partNumber": 341,
    "partName": "PRIMARY SCHOOL TOWN AREA JEWAR ROOM NO 1"
  },
  {
    "partNumber": 342,
    "partName": "PRIMARY SCHOOL TOWN AREA JEWAR ROOM NO 2"
  },
  {
    "partNumber": 343,
    "partName": "PRIMARY SCHOOL TOWN AREA JEWAR ROOM NO 3"
  },
  {
    "partNumber": 344,
    "partName": "JANTA INTER COLLEGE JEWAR TOWN AREA ROOM NO 1"
  },
  {
    "partNumber": 345,
    "partName": "JANTA INTER COLLEGE JEWAR TOWN AREA ROOM NO 2"
  },
  {
    "partNumber": 346,
    "partName": "JANTA INTER COLLEGE JEWAR TOWN AREA ROOM NO 3"
  },
  {
    "partNumber": 347,
    "partName": "JANTA INTER COLLEGE JEWAR TOWN AREA ROOM NO 4"
  },
  {
    "partNumber": 348,
    "partName": "JANTA INTER COLLEGE JEWAR TOWN AREA ROOM NO 5"
  },
  {
    "partNumber": 349,
    "partName": "JANTA INTER COLLEGE JEWAR TOWN AREA ROOM NO 6"
  },
  {
    "partNumber": 350,
    "partName": "PRIMARY SCHOOL VAINA ROAD JEWAR ROOM NO 1"
  },
  {
    "partNumber": 351,
    "partName": "PRIMARY SCHOOL VAINA ROAD JEWAR ROOM NO 2"
  },
  {
    "partNumber": 352,
    "partName": "PRIMARY SCHOOL VAINA ROAD JEWAR ROOM NO 3"
  },
  {
    "partNumber": 353,
    "partName": "KANWAR TECHNICAL INTER COLLEGE JEWAR TOWN AREA ROOM NO 1"
  },
  {
    "partNumber": 354,
    "partName": "KANWAR TECHNICAL INTER COLLEGE JEWAR TOWN AREA ROOM NO 2"
  },
  {
    "partNumber": 355,
    "partName": "KANWAR TECHNICAL INTER COLLEGE JEWAR TOWN AREA ROOM NO 3"
  },
  {
    "partNumber": 356,
    "partName": "ANGANWADI CENTER ESTABLISHMENT AREA JEWAR BANGAR ROOM NO. 1"
  },
  {
    "partNumber": 357,
    "partName": "ANGANWADI CENTER ESTABLISHMENT AREA JEWAR BANGAR ROOM NO. 2"
  },
  {
    "partNumber": 358,
    "partName": "ANGANWADI CENTER ESTABLISHMENT AREA JEWAR BANGAR ROOM NO. 3"
  },
  {
    "partNumber": 359,
    "partName": "ANGANWADI CENTER ESTABLISHMENT AREA JEWAR BANGAR ROOM NO. 4"
  },
  {
    "partNumber": 360,
    "partName": "ANGANWADI CENTER ESTABLISHMENT AREA JEWAR BANGAR ROOM NO. 5"
  },
  {
    "partNumber": 361,
    "partName": "PRIMARY SCHOOL MIRPUR KUTCH URF KANIGARHI ROOM NO 1"
  },
  {
    "partNumber": 362,
    "partName": "PRIMARY SCHOOL MIRPUR KUTCH URF KANIGARHI ROOM NO 2"
  },
  {
    "partNumber": 363,
    "partName": "PRIMARY SCHOOL GOVINSGARH ROOM NO 1"
  },
  {
    "partNumber": 364,
    "partName": "PRIMARY SCHOOL SHAMSHMNAGAR ROOM NO 1"
  },
  {
    "partNumber": 365,
    "partName": "PRIMARY SCHOOL BHAGWANTPUR CHHATANGA ROOM NO 1"
  },
  {
    "partNumber": 366,
    "partName": "PRIMARY SCHOOL CHHATANGA KHURD ROOM NO 1"
  },
  {
    "partNumber": 367,
    "partName": "PRIMARY SCHOOL JHUPPA NARAYAN SINGH ROOM NO 1"
  },
  {
    "partNumber": 368,
    "partName": "PRIMARY SCHOOL JHUPPA KALAN ROOM NO 1"
  },
  {
    "partNumber": 369,
    "partName": "PRIMARY SCHOOL MEWLA GOPALGARH ROOM NO 1"
  },
  {
    "partNumber": 370,
    "partName": "PRIMARY SCHOOL MEWLA GOPALGARH ROOM NO 2"
  },
  {
    "partNumber": 371,
    "partName": "PRIMARY SCHOOL ALIABAD URF MEHDIPUR ROOM NO 1"
  },
  {
    "partNumber": 372,
    "partName": "PRIMARY SCHOOL MANGRAULI ROOM NO 1"
  },
  {
    "partNumber": 373,
    "partName": "PRIMARY SCHOOL MANGRAULI ROOM NO 2"
  },
  {
    "partNumber": 374,
    "partName": "PRIMARY SCHOOL ALAWALPUR ROOM NO 1"
  },
  {
    "partNumber": 375,
    "partName": "PRIMARY SCHOOL AHMEDPUR CHAURAULI ROOM NO 1"
  },
  {
    "partNumber": 376,
    "partName": "PRIMARY SCHOOL AHMEDPUR CHAURAULI ROOM NO 2"
  },
  {
    "partNumber": 377,
    "partName": "PRIMARY SCHOOL AHMEDPUR CHAURAULI ROOM NO 3"
  },
  {
    "partNumber": 378,
    "partName": "JUNIOR HIGH SCHOOL AHMEDPUR CHAURAULI ROOM NO.1"
  },
  {
    "partNumber": 379,
    "partName": "JUNIOR HIGH SCHOOL AHMEDPUR CHAURAULI ROOM NO.2"
  },
  {
    "partNumber": 380,
    "partName": "PRIMARY SCHOOL BHAVOKARA ROOM NO 1"
  },
  {
    "partNumber": 381,
    "partName": "PRIMARY SCHOOL DAYURAR ROOM NO 1"
  },
  {
    "partNumber": 382,
    "partName": "JUNIOR HIGH SCHOOL CHANCHLI ROOM NO 1"
  },
  {
    "partNumber": 383,
    "partName": "JUNIOR HIGH SCHOOL CHANCHLI ROOM NO 2"
  },
  {
    "partNumber": 384,
    "partName": "PRIMARY SCHOOL AURANGABAD URF HIMAYUPUR ROOM NO 1"
  },
  {
    "partNumber": 385,
    "partName": "INTER COLLEGE TOWN AREA JAHANGIRPUR ROOM NO 1"
  },
  {
    "partNumber": 386,
    "partName": "INTER COLLEGE TOWN AREA JAHANGIRPUR ROOM NO 2"
  },
  {
    "partNumber": 387,
    "partName": "INTER COLLEGE TOWN AREA JAHANGIRPUR ROOM NO 3"
  },
  {
    "partNumber": 388,
    "partName": "INTER COLLEGE TOWN AREA JAHANGIRPUR ROOM NO 4"
  },
  {
    "partNumber": 389,
    "partName": "INTER COLLEGE TOWN AREA JAHANGIRPUR ROOM NO 5"
  },
  {
    "partNumber": 390,
    "partName": "JUNIOR HIGH SCHOOL TOWN AREA JHANGIRPUR ROOM NO 1"
  },
  {
    "partNumber": 391,
    "partName": "PRIMARY SCHOOL TOWN AREA JAHANGIRPUR ROOM NO 1"
  },
  {
    "partNumber": 392,
    "partName": "PRIMARY SCHOOL TOWN AREA JAHANGIRPUR ROOM NO 2"
  },
  {
    "partNumber": 393,
    "partName": "PRIMARY SCHOOL TOWN AREA JAHANGIRPUR ROOM NO 3"
  },
  {
    "partNumber": 394,
    "partName": "PRIMARY SCHOOL CHAK JAHANGIRPUR ROOM NO 1"
  },
  {
    "partNumber": 395,
    "partName": "PRIMARY SCHOOL JAFARGARH MAJRA JAHANGIRPUR ROOM NO 1"
  },
  {
    "partNumber": 396,
    "partName": "PRIMARY SCHOOL CHAK NAGLIA ROOM NO. 1"
  },
  {
    "partNumber": 397,
    "partName": "PRIMARY SCHOOL ALAMPUR HATHALA URF LAUDENA ROOM NO 1"
  },
  {
    "partNumber": 398,
    "partName": "PRIMARY SCHOOL ALAMPUR HATHALA URF LAUDENA ROOM NO 2"
  }
]